<?xml version="1.0" encoding="UTF-8"?>
<!-- generated on 2021-03-22 17:23:32.121902 by $Id$ UNKNOWN
  options: -r sampleRoutes.rou.xml <doubleminus>edgedata-files edgedata.xml -o routesLKW.xml -v <doubleminus>edgedata-attribute qLKW <doubleminus>prefix lkw_ <doubleminus>attributes=type="truck_truck" departLane="best" departSpeed="max" departPos="random"
-->
<routes xmlns:xsi="http://www.w3.org/2001/XMLSchema-instance" xsi:noNamespaceSchemaLocation="http://sumo.dlr.de/xsd/routes_file.xsd">
<!-- begin="0.0" end="1800.0" -->
    <vehicle id="lkw_0_0" depart="0.00" type="truck_truck" departLane="best" departSpeed="max" departPos="random">
        <route edges="178843541 268931682#0 268931659#0 4084166 268931652 42760136 268931654#1 42760135#0 42760135#2 42760135#3 880134845 305869959#1 4084169 53040717 323709010 323709011#0 323709011#2 323709012#0 323709012#1 25876774 25876775#0 25876775#1 181337671#0 280873233 181337547 181336338 144916662 181336164#0 24532138#0"/>
    </vehicle>
    <vehicle id="lkw_0_1" depart="19.15" type="truck_truck" departLane="best" departSpeed="max" departPos="random">
        <route edges="195168321 150661833#0 150661833#1 195130786 376865405#3 376865390#1 268931678 268931683#1 204207294 45085545 5097800 4181088 204207292 178229026#1 178225533 305379130#0 204207308 305325054#2"/>
    </vehicle>
    <vehicle id="lkw_0_2" depart="38.30" type="truck_truck" departLane="best" departSpeed="max" departPos="random">
        <route edges="315906361#3 -315906361#3 -315906361#2 -315906361#1 -315906361#0 -518809865#1 -518809865#0 43793038#1 360072943#0 360072943#1 258979231#0 258979231#1 144932611 144932612 252753975#1 181335262 293281410#0 258979178#1 251066998 251066997#0 101617775#0 101617775#1 101617775#2 5182256 24909171 251065565 176570669#1 185573957#0 150663777 -319999605#7 -319999605#6 -319999605#5 -319999605#4 -319999605#1 -319999605#0 8067185#1 8067185#3 8067185#4 8067185#5 53175161 185576374#0 150837582#1 150837582#2 150837582#3 185579896#0 185579896#1 -185580084#1 185580084#1"/>
    </vehicle>
    <vehicle id="lkw_0_3" depart="57.45" type="truck_truck" departLane="best" departSpeed="max" departPos="random">
        <route edges="404599857#1 404599857#2 23055466#0 23055466#1 23055466#3 23055466#4 23055466#5 299639054 376865290#0 376865290#1 300034825 472148300 867790499#1 253488980 253488984 149899046 204400292 251109201 187060050#2 781345962 300035524 150857432#2 93785423 253488957#0 94586305 500261498 94586298 500261497 150837582#1 150837582#2 150837582#3 185579896#0 185579896#1 53175059#1 53175059#2 187061084 93785463#0 93785463#1 190458990#0 190458990#2 151788685 269017597#0 269017597#1 269017597#2 269017597#3 269017597#4 269017597#5 269017597#6 190458063 377905808#0 377905808#2"/>
    </vehicle>
    <vehicle id="lkw_0_4" depart="76.60" type="truck_truck" departLane="best" departSpeed="max" departPos="random">
        <route edges="187628749#1 -320252634#5 -320252634#3 -320252634#2 -320252634#1 -320252634#0 320222738#1 320256282 320239492#0 320239492#1 -104363155#1 24377359 56185654 56185655#0 56185655#1 189776524 56454445 187057791#0 187057791#1 187057791#2 23137790#2 150543795 56186952#0 56186952#1 35134167#0 35134167#2 35134167#3 276412885 276412658 189877634#0 404477284#1 107085649#1 107085644 191003930#0"/>
    </vehicle>
    <vehicle id="lkw_0_5" depart="95.74" type="truck_truck" departLane="best" departSpeed="max" departPos="random">
        <route edges="431557291 40521205#0 150834642#0 150834642#1 500261497 150837582#1 150837582#2 150837582#3 185579896#0 185579896#1 -185580084#1 -185580084#0 -149352823#1"/>
    </vehicle>
    <vehicle id="lkw_0_6" depart="114.89" type="truck_truck" departLane="best" departSpeed="max" departPos="random">
        <route edges="4404114#0 4404114#1 4404114#3 4404114#4 195130786 376865405#3 376865390#1 268931678 268931683#1 204207294 45085545 5097800 4181088 204207292 178229026#1 178225533 178225534 18694413 178226651#1 305390361#2 305390361#3 189575384#1 189575384#2 189575384#3 189575384#4"/>
    </vehicle>
    <vehicle id="lkw_0_7" depart="134.04" type="truck_truck" departLane="best" departSpeed="max" departPos="random">
        <route edges="164095588#2 305325048#0 305325046 305325049#0 305325049#1 305325049#2 236994807 5073592#0 5073592#2 5073592#3 5073592#4 5073592#5 14103491#0 251987384#0 251987384#1 251987384#2 251987384#3 269001615#1 235391298 237023442#0 269001613#0 269001613#1 150694616#2 323709012#0 323709012#1 25876774 25876775#0 25876775#1 181337671#0 280873233 181337547 181336338 396385838 181337215 188324464 102526743#0 102526743#2 144934063 144932088#0 152412638#0 152412638#1 171569487 181332523#0 181332523#1 181332523#2 181332526 426912948#0 426912948#1 426912948#2 426912948#5 426452841#0 383597641#0 383597641#2 383597641#3 383597641#4 383597641#5 383597641#6 190053109#0 190053109#1 190053109#3 25851182#0 25851182#1 25851182#2 25851182#3 27191681#1 -152924684"/>
    </vehicle>
    <vehicle id="lkw_0_8" depart="153.19" type="truck_truck" departLane="best" departSpeed="max" departPos="random">
        <route edges="29350090 320202776 150546874#1 320210276 320210275 320221191 56185655#0 56185655#1 189776524 56454445 187057791#0 187057791#1 187057791#2 471554672 184227241#0 184227241#1 184227241#2 184227241#4 292947985 150395822 25589596 27134171 14189055 5111817 26408353 114976950 74539230#0 74539230#1 225198733#0 251327592#1 77122439#0 77122439#1 480590963#0 480590963#1 480590961 480590958 480590956 77122422#1 77122422#2 480590954 749289063#1 252533204#2 252533204#3 252533204#4"/>
    </vehicle>
    <vehicle id="lkw_0_9" depart="172.34" type="truck_truck" departLane="best" departSpeed="max" departPos="random">
        <route edges="366073486 282331232#0 282331232#1 149888264#1 203461111 -238870176#3 -238870176#2 -238870176#0 -205190519 23567307 269040918 251106111#0 189032454 269040914 385970249#2 385970249#3 305792174#2"/>
    </vehicle>
    <vehicle id="lkw_0_10" depart="191.49" type="truck_truck" departLane="best" departSpeed="max" departPos="random">
        <route edges="-38152916#0 -150851814#6 -150851814#5 -150851814#4 33083418#0 33083418#2 190443836#2 190443836#4 189769943#0 269040916 190446522#0"/>
    </vehicle>
    <vehicle id="lkw_0_11" depart="210.64" type="truck_truck" departLane="best" departSpeed="max" departPos="random">
        <route edges="-532149775#1 -532149775#0 779043553#0 779043553#1 779043553#2 779043553#3 188462687#0 8067185#1 8067185#3 8067185#4 8067185#5 53175161 185576374#0 150837582#1 150837582#2 150837582#3 185579896#0 185579896#1"/>
    </vehicle>
    <vehicle id="lkw_0_12" depart="229.79" type="truck_truck" departLane="best" departSpeed="max" departPos="random">
        <route edges="-131229614#2 -131229614#0 47214333#3 187628738#0 150547351#0 150547351#1 150547351#2 150547351#3 150547351#4 320185500#0 320185500#1 320185500#3 270655640 270655641 189899508 360065008 268931669 268931672#0 268931670 268931671 4235244 204207303#0 164095588#2 204207294"/>
    </vehicle>
    <vehicle id="lkw_0_13" depart="248.94" type="truck_truck" departLane="best" departSpeed="max" departPos="random">
        <route edges="24554371#2 24554371#3 24554371#4 208424704#0 -366073490#0 150697173#0 150697173#1 94586298 500261497 150837582#1 150837582#2 150837582#3 185579896#0 185579896#1 53175059#1 53175059#2 187061084 93785463#0 93785463#1 190458990#0 190458990#2 151788685 269017597#0 269017597#1 269017597#2 269017597#3 269017597#4 269017597#5 269017597#6 190458063 377905808#0 377905808#2 377905809#2 377905809#3"/>
    </vehicle>
    <vehicle id="lkw_0_14" depart="268.09" type="truck_truck" departLane="best" departSpeed="max" departPos="random">
        <route edges="171506614#0 144934058#0 144934063 144932088#0 80587514 171506608#0 171506608#1 252753975#1 181335262 293281410#0 144916662 181336164#0 181336164#1 181336164#2 181336164#3 181336164#4 181336164#5 181336164#6 181336164#7 78489606 178235948#0 178235948#1 178235035 178226533#0 178226496 301704185#0 178229025#5 204207291 5097799 4235242#0 164086589 164086593 45085542#0 268931673#1 270655631 270655638 220911179 189899976 561882213#0 561882213#1 320185059 190022224#1 115738329#0 29350090 320202776 150546874#1 320210276 320210275 320221191 56185655#0 56185655#1 189776524 56454445 187057791#0 187057791#1 187057791#2 471554672 184227241#0 184227241#1 184227241#2 184227241#4 292947985 150395822 25589596 27134171 14189055 5111817 26408353 48278503#0 48278503#2 14189058#0 220914101 480583012#1 286708820 225198728#0 225198728#2 74153953#1 267967579 267967581 18823654 321703404"/>
    </vehicle>
    <vehicle id="lkw_0_15" depart="287.23" type="truck_truck" departLane="best" departSpeed="max" departPos="random">
        <route edges="255389621#0 255389621#1 255389621#2 255389621#3 165849626 4404113#0 4404113#1 4404113#3 268931687 376865405#3 376865390#1 268931678 268931683#1 204207294 45085545 5097800 4181088 204207292 178229026#1 178225533 305379130#0 204207308 305325054#2 152378964 178203529#0 178203529#1 178203529#2 267411688#0 267411688#1 209319564#0 209319564#2 209319564#3 209319564#4 -209497701#1 209497701#1"/>
    </vehicle>
    <vehicle id="lkw_0_16" depart="306.38" type="truck_truck" departLane="best" departSpeed="max" departPos="random">
        <route edges="149899941 253488977#0 42760138 187060052 149904354 53175058 315426058#1 315426061 315426063 315426062 204400292 251109201 187060050#2 781345962 300035524 150857432#2 93785423 253488957#0 108404031#0 4432618#2 -502060955#0"/>
    </vehicle>
    <vehicle id="lkw_0_17" depart="325.53" type="truck_truck" departLane="best" departSpeed="max" departPos="random">
        <route edges="43795168#6 43795168#7 43795168#8 194765169#2 43792812#1 43792812#2 -518809865#1 -518809865#0 43793038#1 360072943#0 360072943#1 258979231#0 258979231#1 144932611 144932612 252753975#1 181335262 293281410#0 144916662 181336164#0 181336164#1 181336164#2 181336164#3 181336164#4 181336164#5 181336164#6 181336164#7 78489606 178235948#0 178235948#1 178235035 178226533#0 178226496 301704185#0 178229025#5 204207291 5097799 4235242#0 164086589 164086593 45085542#0 268931673#1 270655631 270655638 220911179 189899976 561882213#0 561882213#1 320185059 190022224#1 115738329#0 29350090 27283179#0 27283179#1 -320252634#2 -320252634#1 -320252634#0 320222738#1 31648322#1 31648322#2 31648189 320240823 31648190#0 31648190#1 739924926 739924928#0 739924928#1 739924927#0 739924927#2 240321454#2"/>
    </vehicle>
    <vehicle id="lkw_0_18" depart="344.68" type="truck_truck" departLane="best" departSpeed="max" departPos="random">
        <route edges="187628749#1 -320252634#5 -320252634#3 -320252634#2 -320252634#1 -320252634#0 320222738#1 320256282 320239492#0 320239492#1 -104363155#1 24377359 56185654 56185655#0 56185655#1 189776524 56454445 187057791#0 187057791#1 187057791#2 23137790#2 150543795 56186952#0 56186952#1 35134167#0 35134167#2 35134167#3 276412885 276412658 189877634#0 404477284#1 107085649#1 107085644 191003930#0"/>
    </vehicle>
    <vehicle id="lkw_0_19" depart="363.83" type="truck_truck" departLane="best" departSpeed="max" departPos="random">
        <route edges="150770619#1 -238870176#3 -238870176#2 -238870176#0 -205190519 23567307 269040918 251106111#0 189032454 269040914 150770614#1 33083535#0"/>
    </vehicle>
    <vehicle id="lkw_0_20" depart="382.98" type="truck_truck" departLane="best" departSpeed="max" departPos="random">
        <route edges="27245673#7 -27245673#7 -27245673#6 -27245673#5 -27245673#4 -27245673#3 -27245673#2 -27245673#1 93785463#1 190458990#0 190458990#2 151788685 163440758 42760868 163443100#0 163443100#1 269017594 95170298 191640848#0 191640848#1 53175060#0 53175060#1 53175060#2 724854350#0 724854350#1 95170291#0 95170291#1 95170291#3 95170291#4 253488954#0 53175163#1 253488943 253488947 -150697173#1 -150697173#0 366073489#3 366073490#1 366073490#2 366073490#3 230602997#0 230602997#1 230602997#2 24666916 366073460#1 366073459#0 189032454 269040914 385970249#2 385970249#3 305792174#2 305792174#3 305792174#4 249599484#0 249599484#1 249599484#2 249599484#3 238870175#0 -238870175#0"/>
    </vehicle>
    <vehicle id="lkw_0_21" depart="402.13" type="truck_truck" departLane="best" departSpeed="max" departPos="random">
        <route edges="-125927750#4 -125927750#3 -125927750#2 -125927750#1 -125927750#0 -436584039#5 -436584039#4 -436584039#3 -436584039#2 -436584039#1 -436584039#0 -804610969 360072943#0 360072943#1 258979231#0 258979231#1 144932611 144932612 252753975#1 181335262 293281410#0 258979178#1 251066998 251066997#0 101617775#0 101617775#1 101617775#2 5182256 24909171 251065565 176570669#1 185573957#0 150663777 -319999605#7 -319999605#6 -319999605#5 -319999605#4 -319999605#1 -319999605#0 8067185#1 8067185#3 8067185#4 8067185#5 53175161 185576374#0 150837582#1 150837582#2 150837582#3 185579896#0 185579896#1 53175059#1 -33083988#1 -33083988#0"/>
    </vehicle>
    <vehicle id="lkw_0_22" depart="421.28" type="truck_truck" departLane="best" departSpeed="max" departPos="random">
        <route edges="27429649 753460698 25891699 359948072 184156818 184156828 56185654 56185655#0 56185655#1 189776524 56454445 187057791#0 187057791#1 187057791#2 471554672 184227241#0 184227241#1 184227241#2 184227241#4 292947985 150395822 25589596 27134171 14189055 5111817 26408353 114976950 74539230#0 74539230#1 225198733#0 251327592#1 77122439#0 77122439#1 480590963#0 480590963#1 480590961 480590958 480590956 77122422#1 77122422#2 480590954 -749288423#0 -749288422 749288422"/>
    </vehicle>
    <vehicle id="lkw_0_23" depart="440.43" type="truck_truck" departLane="best" departSpeed="max" departPos="random">
        <route edges="255393423 165849627#0 165849627#1 165849627#2 165849627#3 165849627#5 165849627#6 165849627#7 165849627#8 165849627#9 376865290#0 376865290#1 300034825 472148300 867790499#1 253488980 253488984 149899046 149899941 253488977#0 42760138 187060052 149904354 218778912 268931658 42760136 268931654#1 42760135#0 42760135#2 42760135#3 880134845 305869959#1 4084169 53040717 323709010 323709011#0 323709011#2 323709012#0 323709012#1 25876774 25876775#0 25876775#1 181337671#0 280873233 181337547 181336338 396385838 181337215 188324464 102526743#0 102526743#2 144934063 144932088#0 152412638#0 152412638#1 171569487 181332523#0 -181332523#0 -171569487 162611244#0"/>
    </vehicle>
    <vehicle id="lkw_0_24" depart="459.57" type="truck_truck" departLane="best" departSpeed="max" departPos="random">
        <route edges="183413425 235390974 235391021 235391020#0 235391020#1 235391022 396381365 235389907 235389906 235389908#0 269001612#2 269001612#3 269001612#4 269001612#5 235390248#0 235390248#1 305325046 305325049#0 305325049#1 305325049#2 236994807 5073592#0 5073592#2 5073592#3 5073592#4 5073592#5 14103491#0 251987384#0 251987384#1 251987384#2 251987384#3 269001615#1 235391298 237023442#0 269001613#0 269001613#1 150694616#2 323709012#0 323709012#1 25876774 25876775#0 25876775#1 181337671#0 280873233 181337547 181336338 396385838 181337215 188324464 188324465#0 188324465#2 188324465#3 360073480 100302818#1 100302818#2 100302818#3 310396738 456934814 14103952 456934815 404190175 202105825#0 202105825#1 202105823#2 202105823#3 405312618"/>
    </vehicle>
    <vehicle id="lkw_0_25" depart="478.72" type="truck_truck" departLane="best" departSpeed="max" departPos="random">
        <route edges="190340311 182489957#0 182489957#1 182489957#2 182489957#3 -371306931 -190340310 376849860#1 -114928357 114928360#1 376846888 402016776 40584784 187060049#0 187060049#1 561882212 115738329#0 29350090 320202776 150546874#1 320210276 320210275 320221191 56185655#0 56185655#1 189776524 56454445 187057791#0 187057791#1 187057791#2 23137790#2 150543795 56186952#0 56186952#1 35134167#0 35134167#2 35134167#3 276412885 276412658 189877634#0 96747828#0 96747828#1 56185651#3 251161934#0 226991208#0 228126461#1 462537200#1 249375697#1 433018231 433018232 269040901#0 269040901#1 189772874#0 190451914#1 251106575 251106198#0 251106198#2 23567307 269040918 251106111#0 189032454 269040914 385970249#2 385970249#3 305792174#2 305792174#3 305792174#4 249599484#0 -249599484#0"/>
    </vehicle>
    <vehicle id="lkw_0_26" depart="497.87" type="truck_truck" departLane="best" departSpeed="max" departPos="random">
        <route edges="-150694624#3 364080663#2 319999605#4 319999605#5 319999605#6 319999605#7 4084169 53040717 323709010 323709011#0 323709011#2 323709012#0 323709012#1 25876774 25876775#0 25876775#1 181337671#0 280873233 181337547 181336338 396385838 181337215 188324464 102526743#0 102526743#2 144934063 144932088#0 152412638#0 152412638#1 171569487 181332523#0 181332523#1 181332523#2 181332526 426912948#0 426912948#1 426912948#2 426912948#5 426452841#0 383597641#0 383597641#2 383597641#3 383597641#4 383597641#5 383597641#6 190053109#0 190053109#1 190053109#3 190053109#4 190053109#5 204526318#1 204526318#2 204526318#3 204526318#5 204526318#6 204526318#7 204526316#0 204526316#1 204526316#2 397035969 22026968#0 22026968#1 22026968#3"/>
    </vehicle>
    <vehicle id="lkw_0_27" depart="517.02" type="truck_truck" departLane="best" departSpeed="max" departPos="random">
        <route edges="17977155#1 127606907#0 127606907#1 251102618 251102624#0 251102624#2 205190519 23567306#0 23567306#1 23567306#2 269040899 190451409 269040904 230602993 190438083#0 190438083#1 269040907#0 269040907#1 204400292 251109201 187060050#2 781345962 300035524 150857432#2 93785423 253488957#0 94586305 500261498 94586298 500261497 150837582#1 150837582#2 150837582#3 185579896#0 185579896#1 95170297#0 53175060#0 53175060#1 24549659 97142258 -53175159#8 -53175159#7 26923739#0 26923739#1"/>
    </vehicle>
    <vehicle id="lkw_0_28" depart="536.17" type="truck_truck" departLane="best" departSpeed="max" departPos="random">
        <route edges="89478024#1 89478026 508099915#0 508099915#1 258979254#0 258979254#1 258979254#2 258979269#1 227062818#1 227062818#3 227062818#4 227062813#0 227062813#1 227062813#2 227062813#3 258979261 255391114#0 475679571#0 475679571#1 475679571#2 475679571#3 402016820#0 187060058#0 187060058#3 187060057#0 42760132 371300204#0 190032739 371300202"/>
    </vehicle>
    <vehicle id="lkw_0_29" depart="555.32" type="truck_truck" departLane="best" departSpeed="max" departPos="random">
        <route edges="150393270#9 150393270#10 150393270#11 150393270#12 121805107#0 121805107#1 121805107#2 32280972#5 32280972#0 32280972#1 121805100 189889903#0 189889903#1 -150393273#3 -150393273#1 -150393273#0 -360787852#3 -360787852#2 -360787852#0 -5475488#1 23137790#2 150543795 56186952#0 56186952#1 35134167#0 35134167#2 35134167#3 276412885 276412658 189877634#0 96747828#0 96747828#1 56185651#3 251161934#0 226991208#0 228126461#1 462537200#1 249375697#1 433018231 433018232 269040901#0 269040901#1 189772874#0 190451409 269040904 230602993 190438083#0 190438083#1 269040907#0 269040907#1 204400292 251109201 187060050#2 781345962 300035524 46967474#0 46967474#1 46967473 -28297618#1 4432618#0"/>
    </vehicle>
    <vehicle id="lkw_0_30" depart="574.47" type="truck_truck" departLane="best" departSpeed="max" departPos="random">
        <route edges="27287268 -532149775#0 779043553#0 779043553#1 779043553#2 779043553#3 188462687#0 8067185#1 8067185#3 8067185#4 8067185#5 53175161 185576374#0 53175163#1 253488943 253488947 -150697173#1 -150697173#0 366073489#3 366073490#1 366073490#2 366073490#3 230602997#0 230602997#1 230602997#2 24666916 366073460#1 366073459#0 189032454 269040914 385970249#2 385970249#3 305792174#2 305792174#3"/>
    </vehicle>
    <vehicle id="lkw_0_31" depart="593.62" type="truck_truck" departLane="best" departSpeed="max" departPos="random">
        <route edges="235389908#0 269001612#2 269001612#3 269001612#4 269001612#5 235390248#0 235390248#1 305325046 305325049#0 305325049#1 305325049#2 236994807 236994808 252024823#0 252024823#2 268931656 236995001 268931659#0 4084166 268931652 190347317#0 187060053#0 42760134 187060055 53175058 315426058#1 315426061 315426063 315426062 150000852 150000376#2 189773010#0 189773010#1 149996793 9040997 251158323 251158324#1 251158322#0 548514765 228126460#0 316778911#0 287186149#1 251161865#1 7980446#1 7980446#2 7980446#3"/>
    </vehicle>
    <vehicle id="lkw_0_32" depart="612.77" type="truck_truck" departLane="best" departSpeed="max" departPos="random">
        <route edges="37811442#0 37811442#2 387015289#0 387015289#1 165849627#5 165849627#6 165849627#7 165849627#8 165849627#9 376865290#0 376865290#1 300034825 472148300 867790499#1 253488980 149898017#0 150000852 150000376#2 189773010#0 189773010#1 149996793 9040997 251158323 251158324#1 161847017 433018233#0 433018233#1 433018233#2 114198529 191128494 385966809#0"/>
    </vehicle>
    <vehicle id="lkw_0_33" depart="631.91" type="truck_truck" departLane="best" departSpeed="max" departPos="random">
        <route edges="208424704#0 -366073490#0 150697173#0 150697173#1 94586298 500261497 150837582#1 150837582#2 150837582#3 185579896#0 185579896#1 53175059#1 53175059#2 187061084 93785463#0 93785463#1 190458990#0 190458990#2 151788685 269017597#0 269017597#1 269017597#2 269017597#3 269017597#4 269017597#5 269017597#6 190458063 190458064#2 190458064#3 190458064#4 190458064#5 57381284 4391007#0 175344381#0 175344381#1 175344381#2 35099540#0 35099540#1 35099540#2 53040714 -129735587#2 -156466418#5"/>
    </vehicle>
    <vehicle id="lkw_0_34" depart="651.06" type="truck_truck" departLane="best" departSpeed="max" departPos="random">
        <route edges="181335262 293281410#0 258979178#1 251066998 251066997#0 101617775#0 101617775#1 101617775#2 5182256 24909171 251065565 176570669#1 185573957#0 150663777 -319999605#7 -319999605#6 -319999605#5 -319999605#4 -319999605#1 -319999605#0 8067185#1 8067185#3 8067185#4 8067185#5 53175161 185576374#0 150837582#1 150837582#2 150837582#3 185579896#0 185579896#1 53175059#1 33083987#0 -33083987#0"/>
    </vehicle>
    <vehicle id="lkw_0_35" depart="670.21" type="truck_truck" departLane="best" departSpeed="max" departPos="random">
        <route edges="47214333#1 47214333#2 47214333#3 187628738#0 270905178#0 29350090 320202776 150546874#1 320210276 320210275 320221191 56185655#0 56185655#1 189776524 56454445 187057791#0 187057791#1 187057791#2 471554672 184227241#0 184227241#1 184227241#2 184227241#4 292947985 150395822 25589596 27134171 14189055 5111817 26408353 48278503#0 48278503#2 14189058#0 220914101 295555117#1 253620469"/>
    </vehicle>
    <vehicle id="lkw_0_36" depart="689.36" type="truck_truck" departLane="best" departSpeed="max" departPos="random">
        <route edges="227062813#3 258979261 255391114#0 475679571#0 475679571#1 475679571#2 475679571#3 402016820#0 187060058#0 187060058#3 187060057#0 42760132 85270645 320185351 320185500#0"/>
    </vehicle>
    <vehicle id="lkw_0_37" depart="708.51" type="truck_truck" departLane="best" departSpeed="max" departPos="random">
        <route edges="7942136#1 409702806#1 438279356 179527904#1 508099915#0 508099915#1 258979265#0 258979265#1 628505597 165828294#0 581663849 360248203#1 360248191 360248194 360248197#0 360248197#1 360248209#1 268931670 268931671 4235244 204207303#0 164095588#2 305325048#0 305325046 305325049#0 305325049#1 305325049#2 236994807 5073592#0 5073592#2 5073592#3 5073592#4 5073592#5 14103491#0 251987384#0 251987384#1 251987384#2 251987384#3 269001615#1 235391298 237023442#0 269001613#0 269001613#1 150694616#2 323709012#0 323709012#1 25876774 25876775#0 25876775#1 181337671#0 280873233 181337547 181336338 144918027#1 144918027#2 144918027#3 461562479#0 461562479#2 181334581#1"/>
    </vehicle>
    <vehicle id="lkw_0_38" depart="727.66" type="truck_truck" departLane="best" departSpeed="max" departPos="random">
        <route edges="150697174#0 -150697174#0 -366073486 24666916 366073460#1 366073459#0 189032454 269040914 385970249#2 -385970249#2"/>
    </vehicle>
    <vehicle id="lkw_0_39" depart="746.81" type="truck_truck" departLane="best" departSpeed="max" departPos="random">
        <route edges="127606907#0 127606907#1 251102618 251102624#0 251102624#2 205190519 23567306#0 23567306#1 23567306#2 269040899 190451409 269040904 230602993 190438083#0 190438083#1 269040907#0 269040907#1 204400292 251109201 187060050#2 781345962 300035524 46967474#0 46967474#1 46967473 -28297618#1 -28297618#0 -262140928 -27261757#3 -27261757#2 -268931675#2"/>
    </vehicle>
    <vehicle id="lkw_0_40" depart="765.96" type="truck_truck" departLane="best" departSpeed="max" departPos="random">
        <route edges="208424704#0 -366073490#0 150697173#0 150697173#1 94586298 500261497 150837582#1 150837582#2 150837582#3 185579896#0 185579896#1 53175059#1 53175059#2 187061084 93785463#0 93785463#1 190458990#0 190458990#2 151788685 269017597#0 269017597#1 269017597#2 269017597#3 269017597#4 269017597#5 269017597#6 190458063 190458064#2 190458064#3 190458064#4 190458064#5 57381284 4391007#0 175344381#0 175344381#1 175344381#2 35099540#0 35099540#1 35099540#2 53040714 -129735587#2 -156466418#5"/>
    </vehicle>
    <vehicle id="lkw_0_41" depart="785.11" type="truck_truck" departLane="best" departSpeed="max" departPos="random">
        <route edges="25990734 -103821555 -566297442 -25990739#3 -25990739#2 -25990739#1 -178199022#0 778957164#0 778957164#1 178206109#0 178206109#1 178205027 204207289 18695339#0 178229026#1 178225533 178225534 18694413 301704201#0 301704201#1 301704201#2 251071274 251071273#0 251071273#1 251071273#2 280873237#1 280873237#2 280873237#3 283996821#0 280873233 181337547 181336338 396385838 181337215 188324464 102526743#0 102526743#2 144934063 144932088#0 152412638#0 152412638#1 171569487 181332523#0 181332523#1 181332523#2 181332526 426912948#0 426912948#1 426912948#2 426912948#5 426452841#0 -18314022#4 -18314022#3 -18314022#2 -18314022#1 -18314022#0 -436584061#1 -436584061#0 -125927750#6 -125927750#5 -125927750#4 -125927750#3 -125927750#2 -125927750#1 -125927750#0 -436584039#5 22331296#0 -22331296#0"/>
    </vehicle>
    <vehicle id="lkw_0_42" depart="804.26" type="truck_truck" departLane="best" departSpeed="max" departPos="random">
        <route edges="-4492383#1 24608208#1 163419466#3 163419466#4 163419466#7 185352101 150697171#1 319999605#1 319999605#4 319999605#5 319999605#6 319999605#7 4084169 150663777 185573958 237278283 237278282#3 268931664#1 268931665 147683978#0 4084166 4432606#1 4432606#2 4432606#3 4432606#4 4432606#5 4432606#6 4404116#0 4404116#1 4404116#2 4404116#3 255389621#2 255389621#3 165849626 165849630#0 150551277#2 363826076 628505596 190431168#1 190431168#2 227062818#1 227062818#3 227062818#4 227062813#0 227062813#1 227062813#2 227062813#3 258979261"/>
    </vehicle>
    <vehicle id="lkw_0_43" depart="823.40" type="truck_truck" departLane="best" departSpeed="max" departPos="random">
        <route edges="320252634#9 -320252634#9 -320252634#8 -320252634#5 -320252634#3 -320252634#2 -320252634#1 -320252634#0 320222738#1 320256282 320239492#0 320239492#1 -104363155#1 24377359 56185654 56185655#0 56185655#1 189776524 56454445 187057791#0 187057791#1 187057791#2 471554672 184227241#0 184227241#1 184227241#2 184227241#4 292947985 150395822 25589596 27134171 14189055 5111817 26408353 48278503#0 48278503#2 14189058#0 220914101 480583012#1 286708820 225198728#0 225198728#2 74153953#1 267967579 267967608 295539968 267967594 267967597 42761340#0 42761340#1 42761340#2 42761340#3 42761340#4 42761340#5"/>
    </vehicle>
    <vehicle id="lkw_0_44" depart="842.55" type="truck_truck" departLane="best" departSpeed="max" departPos="random">
        <route edges="27245673#10 -27245673#10 -27245673#9 -27245673#8 -27245673#7 -27245673#6 -27245673#5 -27245673#4 -27245673#3 -27245673#2 -27245673#1 93785463#1 190458990#0 190458990#2 151788685 163419805#0 163419805#1 163419805#2 163419466#0 163419466#1 163419466#3 163419466#4 163419466#7 185352101 150697171#1 319999605#1 319999605#4 319999605#5 319999605#6 319999605#7 4084169 53040717 323709010 323709011#0 323709011#2 323709012#0 323709012#1 25876774 25876775#0 25876775#1 181337671#0 280873233 181337547 181336338 396385838 181337215 188324464 102526743#0 102526743#2 144934063"/>
    </vehicle>
    <vehicle id="lkw_0_45" depart="861.70" type="truck_truck" departLane="best" departSpeed="max" departPos="random">
        <route edges="178206109#0 178206109#1 178205027 204207289 18695339#0 178229025#5 204207291 5097799"/>
    </vehicle>
    <vehicle id="lkw_0_46" depart="880.85" type="truck_truck" departLane="best" departSpeed="max" departPos="random">
        <route edges="870453325 -870453325 -50919061#3 -50919061#2 -50919061#1 -50919061#0 -229460712#1 -229460712#0 25948331 516863395#0 516863395#1 258194205 150398308 456934817 184156805 150398305 8611964 184156816 184156815 5466445#0 190340312 216879571 674280493 102774826 102749569 4474685 24377358 85287424 85287423#0 187060058#0 187060058#3 187060057#0 42760132 85270645 320185351 320185500#0 320185500#1 320185500#3 270655640 270655641 189899508 360065008 268931669 268931672#0 268931670 268931671 4235244 204207303#0 164095588#2 305325048#0 305325046 305325049#0 305325049#1 305325049#2 236994807 5073592#0 5073592#2 5073592#3 5073592#4 5073592#5 14103491#0 251987384#0 251987384#1 251987384#2 251987384#3 269001615#1 235391298 150694607#0 150694607#2 183654500#0 183654500#1 183413425 235390974 235391021 235391020#0 235391020#1"/>
    </vehicle>
    <vehicle id="lkw_0_47" depart="900.00" type="truck_truck" departLane="best" departSpeed="max" departPos="random">
        <route edges="-306029065#1 306029065#1 -40586130#0 -35014373#2 -35014373#1 -35014373#0 -739924926 -31648190#1 -31648190#0 -402016793 -31648189 128081143 320239489#0 320237745 320252264 265910769 320252634#1 320252634#2 -27283179#1 -27283179#0 320202776 475679571#0 475679571#1 475679571#2 475679571#3 402016820#0 187060058#0 187060058#3 187060057#0 42760132 85270645 320185351 320185500#0 320185500#1 320185500#3 270655640 270655641 189899508 360065008 268931669 268931672#0 268931670 268931671 4235244 204207303#0 164095588#2 305325048#0 305325046 305325049#0 305325049#1 305325049#2 236994807 5073592#0 5073592#2 5073592#3 5073592#4 5073592#5 14103491#0 251987384#0 251987384#1 251987384#2 251987384#3 269001615#1 235391298 237023442#0 269001613#0 269001613#1 150694616#2 323709012#0 323709012#1 25876774 25876775#0 25876775#1 181337671#0 280873233 181337547 181336338 396385838 181337215 188324464 102526743#0 102526743#2 144934063 144932088#0 152412638#0 152412638#1 171569487 181332523#0 181332523#1 181332523#2 181332526 426912948#0 426912948#1 426912948#2 426912948#5 426452841#0 -18314022#4 -18314022#3 -18314022#2 -18314022#1 -18314022#0 -436584061#1 -436584061#0 -125927750#6 -125927750#5 -125927750#4 -125927750#3 -125927750#2 125927750#2"/>
    </vehicle>
    <vehicle id="lkw_0_48" depart="919.15" type="truck_truck" departLane="best" departSpeed="max" departPos="random">
        <route edges="25777798 209767602#4 209319563#2 209319563#3 152376333#0 152376333#1 152376333#2 152376333#3 150667574#0 150667574#1 204207290#0 204207290#1 204207290#4 267411640#0 267411640#2 178206585 178205028 204207289 18695339#0 178229026#1 178225533 178225534 18694413 301704201#0 301704201#1 301704201#2 251071274 251071273#0 251071273#1 251071273#2 280873237#1 280873237#2 280873237#3 283996821#0 280873233 181337547 181336338 396385838 181337215 188324464 102526743#0 102526743#2 144934063 144932088#0 152412638#0 152412638#1 171569487 181332523#0 181332523#1 181332523#2 181332526 426912948#0 426912948#1 426912948#2 426912948#5 426452841#0 383597641#0 383597641#2 383597641#3 383597641#4 383597641#5 383597641#6 190053109#0 190053109#1 190053109#3 190053109#4 190053109#5 204526318#1 204526318#2 204526318#3"/>
    </vehicle>
    <vehicle id="lkw_0_49" depart="938.30" type="truck_truck" departLane="best" departSpeed="max" departPos="random">
        <route edges="366073489#2 366073489#3 366073490#1 366073490#2 366073490#3 230602997#0 230602997#1 230602997#2 24666916 366073460#1 366073459#0 189032454 269040914 150770614#1 33083535#0"/>
    </vehicle>
    <vehicle id="lkw_0_50" depart="957.45" type="truck_truck" departLane="best" departSpeed="max" departPos="random">
        <route edges="150697174#0 -150697174#0 -366073486 24666916 366073460#1 366073459#0 189032454 269040914 385970249#2 -385970249#2"/>
    </vehicle>
    <vehicle id="lkw_0_51" depart="976.60" type="truck_truck" departLane="best" departSpeed="max" departPos="random">
        <route edges="112562464 46967473 -28297618#1 4432618#0 364080662#1 94586305 500261498 94586298 500261497 150837582#1 150837582#2 150837582#3 185579896#0 185579896#1 53175059#1 53175059#2 187061084 93785463#0 93785463#1 190458990#0 190458990#2 151788685 269017597#0 269017597#1 269017597#2 269017597#3 269017597#4 269017597#5 269017597#6 190458063 190458064#2 190458064#3"/>
    </vehicle>
    <vehicle id="lkw_0_52" depart="995.74" type="truck_truck" departLane="best" departSpeed="max" departPos="random">
        <route edges="190451409 269040904 230602993 190438083#0 190438083#1 269040907#0 269040907#1 204400292 251109201 187060050#2 781345962 300035524 150857432#2 93785423 253488957#0 94586305 500261498 94586298 500261497 150837582#1 150837582#2 150837582#3 185579896#0 185579896#1 53175059#1 -33083988#1"/>
    </vehicle>
    <vehicle id="lkw_0_53" depart="1014.89" type="truck_truck" departLane="best" departSpeed="max" departPos="random">
        <route edges="42761340#0 42761340#1 42761340#2 42761340#3 42761340#4 42761340#5 42761340#6 42761340#7 42761340#8 267967583#0 267967583#1 74046358 28462311#0 480583011#1 286708821 480583010#0 286708819 127170001#0 127170001#1 127170001#2 74539230#0 74539230#1 225198733#0 251327592#1 77122439#0 77122439#1 -77122446#3 -77122446#2 -77122446#1 -77122446#0 -30163590#4 -30163590#3 -30163590#2 -30163590#1 -30163590#0 -625333807#1 -625333807#0 -50916530#4 -50916530#3 -50916530#2 -50916530#1 -50916530#0 -870453325 -50919061#3 -50919061#2 -50919061#1 -50919061#0 -229460712#1 -229460712#0 25948331 516863395#0 516863395#1 258194205 150398308 456934817 184156805 150398305 8611964 184156816 184156815 5466445#0 190340312 216879571 674280493 102774826 102749569 4474685 24377358 85287424 85287423#0 187060058#0 187060058#3 187060057#0 42760132 371300204#0 190032739 371300202 35925380#1 35925380#2 -35834157#2 -35834157#1 56185657#0 56185657#2 258979227 229917857#1 182489863 190340311 182489957#0"/>
    </vehicle>
    <vehicle id="lkw_0_54" depart="1034.04" type="truck_truck" departLane="best" departSpeed="max" departPos="random">
        <route edges="-38152916#0 -150851814#6 -150851814#5 -150851814#4 33083418#0 33083418#2 190443836#2 190443836#4 189769943#0 269040916 190446522#0"/>
    </vehicle>
    <vehicle id="lkw_0_55" depart="1053.19" type="truck_truck" departLane="best" departSpeed="max" departPos="random">
        <route edges="283996821#0 101617775#0 101617775#1 101617775#2 5182256 24909171 251065565 176570669#1 185573957#0 150663777 -319999605#7 -319999605#6 -319999605#5 -319999605#4 -319999605#1 -319999605#0 8067185#1 8067185#3 8067185#4 8067185#5 53175161 185576374#0 150837582#1 150837582#2 150837582#3 185579896#0 185579896#1 95170297#0 53175060#0 53175060#1 53175060#2 724854350#0"/>
    </vehicle>
    <vehicle id="lkw_0_56" depart="1072.34" type="truck_truck" departLane="best" departSpeed="max" departPos="random">
        <route edges="19354464#1 19354464#2 227062813#0 227062813#1 227062813#2 227062813#3 184156823 24388976 179527910 320254931 140313445#1 31648322#0 320256282 320239492#0 320239492#1 -104363155#1 24377359 56185654 56185655#0 56185655#1 189776524 56454445 187057791#0 187057791#1 187057791#2 471554672 184227241#0 184227241#1 184227241#2 360788356 371573875 371573874 371573876#0 371573876#1 371573876#2 371573876#3 371573876#4 371573876#5 371573876#6 371573876#7 270655645#1 172330768 172332283 241779847 172332636"/>
    </vehicle>
    <vehicle id="lkw_0_57" depart="1091.49" type="truck_truck" departLane="best" departSpeed="max" departPos="random">
        <route edges="-134394675#0 134394171#3 323709012#0 323709012#1 25876774 25876775#0 25876775#1 181337671#0 280873233 181337547 181336338 396385838 181337215 188324464 102526743#0 102526743#2 144934063 144932088#0 152412638#0 152412638#1 171569487 181332523#0 181332523#1 181332523#2 181332526 426912948#0 426912948#1 426912948#2 426912948#5 426452841#0 383597641#0 383597641#2 383597641#3 383597641#4 383597641#5 383597641#6 190053109#0 190053109#1 190053109#3 190053109#4 190053109#5 4434089#0 4434089#1 4434089#2 4434089#3 4434089#4 4434089#5 4434089#6 620270256#0 620270256#1"/>
    </vehicle>
    <vehicle id="lkw_0_58" depart="1110.64" type="truck_truck" departLane="best" departSpeed="max" departPos="random">
        <route edges="-24534195#1 24534195#1 4432614#2 4432614#3 4432614#4 4432614#5 364080662#0 364080662#1 108404033#0 108404033#1 108404033#2 108404033#3 366073490#3 230602997#0 230602997#1 230602997#2 24666916 366073460#1 366073459#0 189032454 269040914 385970249#2 385970249#3 305792174#2"/>
    </vehicle>
    <vehicle id="lkw_0_59" depart="1129.79" type="truck_truck" departLane="best" departSpeed="max" departPos="random">
        <route edges="4404114#1 4404114#3 4404114#4 195130786 376865405#3 376865390#1 268931678 268931683#1 305325048#0 305325046 305325049#0 305325049#1 305325049#2 236994807 5073592#0 5073592#2 5073592#3 5073592#4 5073592#5 14103491#0 251987384#0 251987384#1 251987384#2 251987384#3 269001615#1 235391298 237023442#0 269001613#0 269001613#1 150694616#2 323709012#0 323709012#1 25876774 25876775#0 25876775#1 181337671#0 280873233 181337547 181336338 396385838 181337215 188324464 102526743#0 102526743#2 144934063 144932088#0 152412638#0 152412638#1 171569487 181332523#0 181332523#1 181332523#2 181332526 426912948#0 426912948#1 426912948#2 426912948#5 426452841#0 383597641#0 383597641#2 383597641#3 383597641#4 383597641#5 383597641#6 190053109#0 190053109#1 190053109#3 190053109#4 190053109#5 4434089#0 4434089#1 4434089#2 4434089#3 4434089#4 4434089#5"/>
    </vehicle>
    <vehicle id="lkw_0_60" depart="1148.94" type="truck_truck" departLane="best" departSpeed="max" departPos="random">
        <route edges="27429649 753460698 25891699 359948072 184156818 184156828 56185654 56185655#0 56185655#1 189776524 56454445 187057791#0 187057791#1 187057791#2 471554672 184227241#0 184227241#1 184227241#2 184227241#4 292947985 150395822 25589596 27134171 14189055 5111817 26408353 114976950 74539230#0 74539230#1 225198733#0 251327592#1 77122439#0 77122439#1 480590963#0 480590963#1 480590961 480590958 480590956 77122422#1 77122422#2 480590954 -749288423#0 -749288422 749288422"/>
    </vehicle>
    <vehicle id="lkw_0_61" depart="1168.09" type="truck_truck" departLane="best" departSpeed="max" departPos="random">
        <route edges="27429649 753460698 25891699 359948072 184156818 184156828 56185654 56185655#0 56185655#1 189776524 56454445 187057791#0 187057791#1 187057791#2 471554672 184227241#0 184227241#1 184227241#2 184227241#4 292947985 150395822 25589596 27134171 14189055 5111817 26408353 114976950 74539230#0 74539230#1 225198733#0 251327592#1 77122439#0 77122439#1 480590963#0 480590963#1 480590961 480590958 480590956 77122422#1 77122422#2 480590954 -749288423#0 -749288422 749288422"/>
    </vehicle>
    <vehicle id="lkw_0_62" depart="1187.23" type="truck_truck" departLane="best" departSpeed="max" departPos="random">
        <route edges="27261757#0 27261757#1 -268931675#2 -268931675#1 102486913#0 102486913#1 102486913#3 305869959#1 4084169 53040717 323709010 323709011#0 323709011#2 323709012#0 323709012#1 25876774 25876775#0 25876775#1 181337671#0 280873233 181337547 181336338 396385838 181337215 188324464 102526743#0 102526743#2 144934063 144932088#0 152412638#0 152412638#1 171569487 181332523#0 181332523#1 181332523#2 181332526 426912948#0 426912948#1 426912948#2 426912948#5 426452841#0 383597641#0 383597641#2 383597641#3 383597641#4 -151493314#2 -151493314#1"/>
    </vehicle>
    <vehicle id="lkw_0_63" depart="1206.38" type="truck_truck" departLane="best" departSpeed="max" departPos="random">
        <route edges="-102486913#0 268931675#1 -364071765#0 -4248376 502060953#1 182065983#1 53175058 315426058#1 315426061 315426063 315426062 150000852 150000376#2 189773010#0 189773010#1 149996793 9040997 251158323 251158324#1 251158322#0 548514765 228126460#0 316778911#0 287186149#1 251161865#1 781419324 404599852 404599853 251157594 548514764#2 548514763#0 189876499 160173625 360785921#0 360785921#1 23137784 25589596 27134171 14189055 5111817 26408353 114976950 74539230#0 74539230#1 225198733#0 251327592#1 77122439#0 77122439#1 -77122446#3 -77122446#2 -77122446#1 -77122446#0 -30163590#4 -30163590#3 -30163590#2 -30163590#1 -30163590#0 -625333807#1 -625333807#0 -50916530#4 -50916530#3 -50916530#2 50916530#2"/>
    </vehicle>
    <vehicle id="lkw_0_64" depart="1225.53" type="truck_truck" departLane="best" departSpeed="max" departPos="random">
        <route edges="255389622#5 255389622#6 255389622#8 255389622#9 23263249#0 23263249#1 4403852#4 4403852#5 4403852#6 4403852#7 628505595#0 42760134 187060055 53175058 315426058#1 315426061 315426063 315426062 150000852 150000376#2 189773010#0 189773010#1 149996793 190451914#1 251106575 251106198#0 251106198#2 23567307 269040918 251106111#0 189032454 269040914 269040916 190446522#0 35948952#0 190443836#2"/>
    </vehicle>
    <vehicle id="lkw_0_65" depart="1244.68" type="truck_truck" departLane="best" departSpeed="max" departPos="random">
        <route edges="23137790#2 150543795 56186952#0 56186952#1 35134167#0 35134167#2 35134167#3 276412885 276412658 189876499 160173625 360785921#0 360785921#1 5111851 360785920#0 190340308 399741814#0 399741814#1 190340307 399741671 471554672 184227241#0 184227241#1 184227241#2"/>
    </vehicle>
    <vehicle id="lkw_0_66" depart="1263.83" type="truck_truck" departLane="best" departSpeed="max" departPos="random">
        <route edges="-443340950#1 -443340950#0 129735587#1 129735587#2 -53040714 -35099540#2 -35099540#1 -35099540#0 35099432#0 35099432#2 4084172 114389127#1 114389127#2 114389127#3 114389127#4 377905808#0 377905808#2 377905809#2 377905809#3 377905809#4 269017600#0 269017600#1 163440758 42760868 163443100#0 163443100#1 269017594 95170298 191640848#0 191640848#1 53175060#0 53175060#1 53175060#2 724854350#0 724854350#1 95170291#0 95170291#1 95170291#3 95170291#4 253488954#0 53175163#1 253488943 253488947 253488948 253488950#0 112562464 46967473 502060953#0 502060953#1 182065983#1 53175058 315426058#1 315426061 315426063 315426062 150000852 150556226 404599856 255225031#3 404599855#1 404599857#0 404599857#1 404599857#2 387015293#0 387015293#1 387015293#2 387015293#3 107085661"/>
    </vehicle>
    <vehicle id="lkw_0_67" depart="1282.98" type="truck_truck" departLane="best" departSpeed="max" departPos="random">
        <route edges="251158909#1 107085664#0 107085664#1 107085651#1 432348158 432348156 255225445#0 149996793 190451409 269040904 150770619#1 150770619#4 24725160#0 24725160#1 149888267 -282331232#1 -282331232#0 -366073486 -230602997#2 -230602997#1 -230602997#0 -366073490#3 -366073490#2 -366073490#1 -366073490#0 -366073489#2 -366073489#1 24532464 366073468#1 366073469#1"/>
    </vehicle>
    <vehicle id="lkw_0_68" depart="1302.13" type="truck_truck" departLane="best" departSpeed="max" departPos="random">
        <route edges="558316903 -558316903 48425478#0 48425478#1 -749288423#0 -749288422 -28560402#2 -28560402#1 -28560402#0 791260171 -870453326 -28560406#1 -28560406#0 -229460712#1 -229460712#0 25948331 516863395#0 516863395#1 258194205 150398308 456934817 184156805 150398305 8611964 184156816 184156815 5466445#0 190340312 216879571 674280493 150546872 181503326#0 181503326#1 255392314 255392313#0 387015286 409702806#1 438279356 -150546877#2 150546877#2"/>
    </vehicle>
    <vehicle id="lkw_0_69" depart="1321.28" type="truck_truck" departLane="best" departSpeed="max" departPos="random">
        <route edges="-23055466#4 23055466#4 23055466#5 299639054 376865290#0 376865290#1 300034825 472148300 867790499#1 253488980 253488984 149899046 149899941 253488977#0 42760138 187060052 149904354 218778912 268931658 42760136 268931654#1 42760135#0 42760135#2 42760135#3 880134845 305869959#1 4084169 53040717 323709010 323709011#0 323709011#2 323709012#0 323709012#1 25876774 25876775#0 25876775#1 181337671#0 280873233 181337547 181336338 144918027#1 144918027#2 144918027#3 461562479#0 461562479#2 461562478#1 426912946#0 426912946#1 152406542 181332367#0 123557418 190061812#0 190061812#1 190061812#2 190061812#3 190061812#4 -204526320#1"/>
    </vehicle>
    <vehicle id="lkw_0_70" depart="1340.43" type="truck_truck" departLane="best" departSpeed="max" departPos="random">
        <route edges="190347317#0 187060053#0 42760134 187060055 53175058 315426058#1 315426061 315426063 315426062 204400292 251109201 187060050#2 781345962 300035524 150857432#2 93785423 253488957#0 94586305 500261498 94586298 500261497 150837582#1 150837582#2 150837582#3 185579896#0 185579896#1 53175059#1 53175059#2 187061084 93785463#0 93785463#1 190458990#0 190458990#2 151788685 269017597#0 269017597#1 269017597#2 269017597#3 269017597#4 269017597#5 269017597#6 190458063 190458064#2 190458064#3 190458064#4 190458064#5 57381284 4391007#0 175344381#0 175344381#1 175344381#2 35099540#0 35099540#1 27288175#0 27288175#1 -27288175#1"/>
    </vehicle>
    <vehicle id="lkw_0_71" depart="1359.57" type="truck_truck" departLane="best" departSpeed="max" departPos="random">
        <route edges="216879574#5 216879574#6 165825311#0 165825311#1 165825311#2 190340308 399741814#0 399741814#1 190340307 399741671 471554672 184227241#0 184227241#1 184227241#2 184227241#4 292947985 150395822 25589596 27134171 14189055 5111817 26408353 114976950 74539230#0 74539230#1 225198733#0 251327592#1 77122439#0 77122439#1 -77122446#3 -77122446#2 -77122446#1 -77122446#0 -30163590#4 -30163590#3 -30163590#2 -30163590#1 -30163590#0 -625333807#1 -625333807#0 -50916530#4 -50916530#3 -50916530#2 -50916530#1 -50916530#0 -870453325 -50919061#3 -50919061#2 -50919061#1 -50919061#0 -749003346 -206233781#0 -27571673#2 -27571673#0 255326881 206233778 255326878"/>
    </vehicle>
    <vehicle id="lkw_0_72" depart="1378.72" type="truck_truck" departLane="best" departSpeed="max" departPos="random">
        <route edges="156466418#6 -5199695#3 -5199695#2 -183630189#1 -183630189#0 -53040714 -35099540#2 -35099540#1 -35099540#0 35099432#0 35099432#2 4084172 114389127#1 114389127#2 114389127#3 114389127#4 377905808#0 377905808#2 377905809#2 377905809#3 377905809#4 269017600#0 269017600#1 163440758 42760868 163443100#0 163443100#1 269017594 95170298 191640848#0 191640848#1 53175060#0 53175060#1 53175060#2 724854350#0 724854350#1 95170291#0 95170291#1 95170291#3 95170291#4 253488954#0 53175163#1 253488943 253488947 253488948 253488950#0 112562464 46967473 502060953#0 502060953#1 182065983#1 53175058 315426058#1 315426061 315426063 315426062 150000852 150556226 404599856 255225031#3 404599855#1 404599857#0 404599857#1 404599857#2 23055466#0 23055466#1 23055466#3 23055466#4 23055466#5 299639054 376865290#0 376865290#1 300034825 472148300 867790499#1 253488980"/>
    </vehicle>
    <vehicle id="lkw_0_73" depart="1397.87" type="truck_truck" departLane="best" departSpeed="max" departPos="random">
        <route edges="184156814#0 184156814#2 150543795 56186952#0 56186952#1 35134167#0 35134167#2 35134167#3 276412885 276412658 165825876 191003931#0 191003931#1 227062816 165828294#0 150554195#2 150554195#3 258979269#1 227062820#0 227062820#1 150546880 23055032"/>
    </vehicle>
    <vehicle id="lkw_0_74" depart="1417.02" type="truck_truck" departLane="best" departSpeed="max" departPos="random">
        <route edges="53175163#1 253488943 253488947 -150697173#1 -150697173#0 366073489#3 366073490#1 366073490#2 366073490#3 230602997#0 230602997#1 230602997#2 24666916 366073460#1 366073459#0 189032454 269040914 385970249#2 385970249#3 305792174#2 305792174#3 305792174#4 249599484#0 249599484#1 249599484#2 249599484#3 238870175#0"/>
    </vehicle>
    <vehicle id="lkw_0_75" depart="1436.17" type="truck_truck" departLane="best" departSpeed="max" departPos="random">
        <route edges="500582851#1 255389622#0 255389622#3 255389622#4 255389622#5 255389622#6 255389622#8 255389622#9 255389621#0 255389621#1 255389621#2 255389621#3 165849626 4404113#0 4404113#1 4404113#3 268931687 376865405#3 376865390#1 268931678 268931683#1 204207294 45085545 5097800 4181088 204207292 178229026#1 178225533 178225534 18694413 178226651#1 305390361#2 305390361#3 189575384#1 189575384#2 -23090540#6 -23090540#4 -23090540#3 23090540#3"/>
    </vehicle>
    <vehicle id="lkw_0_76" depart="1455.32" type="truck_truck" departLane="best" departSpeed="max" departPos="random">
        <route edges="5073616#1 5073616#2 5073616#3 112562464 46967473 502060953#0 502060953#1 182065983#1 218778912 268931658 42760136 268931654#1 42760135#0 42760135#2 42760135#3 880134845 305869959#1 4084169 53040717 323709010 323709011#0 323709011#2 323709012#0 323709012#1 25876774 25876775#0 25876775#1 181337671#0 280873233 181337547 181336338 396385838 181337215 188324464 102526743#0 102526743#2 144934063 144932088#0 152412638#0 152412638#1 171569487 181332523#0 181332523#1 181332523#2 181332526 426912948#0 426912948#1 426912948#2 426912948#5 426452841#0 383597641#0 383597641#2 383597641#3 383597641#4 383597641#5 383597641#6 190053109#0 190053109#1 190053109#3 190053109#4 190053109#5 204526318#1 204526318#2 204526318#3 204526318#5 204526318#6 204526318#7 204526316#0 204526316#1 204526316#2 397035969 202133321#0 202133321#2 202133321#3 31113576#0"/>
    </vehicle>
    <vehicle id="lkw_0_77" depart="1474.47" type="truck_truck" departLane="best" departSpeed="max" departPos="random">
        <route edges="-14104725#1 -14104725#0 189032455 127606907#0 127606907#1 251102618 251102624#0 251102624#2 205190519 23567306#0 23567306#1 23567306#2 269040899 9040997 251158323 251158324#1 180858782 23566448#0 23566448#1 189773264 127454278#0 127454278#1 114399554#1 150770354#1 27994938#0 694345941#2 778989042#0 778989042#1 373426447#1 373426447#2 373426448#2 23335658#0 23335658#1 -23335658#1"/>
    </vehicle>
    <vehicle id="lkw_0_78" depart="1493.62" type="truck_truck" departLane="best" departSpeed="max" departPos="random">
        <route edges="123699908#0 4235244 204207303#0 164095588#2 204207294 150549933#0 164086589 164086593 45085542#0 268931673#1 270655631 270655638 150549493#2 -305829911#1 -305829911#0 -182489865 182489859 35834154 182489865"/>
    </vehicle>
    <vehicle id="lkw_0_79" depart="1512.77" type="truck_truck" departLane="best" departSpeed="max" departPos="random">
        <route edges="-266188220#2 -266188220#1 -266188220#0 163419466#1 163419466#3 163419466#4 163419466#7 185352101 8067185#1 8067185#3 8067185#4 8067185#5 53175161 185576374#0 53175163#1 253488943 253488947 -150697173#1 -150697173#0 366073489#3 366073490#1 366073490#2 366073490#3 230602997#0 230602997#1 230602997#2 24666916 366073460#1 366073459#0 189032454 269040914 385970249#2 385970249#3 -14104725#2 -14104725#1"/>
    </vehicle>
    <vehicle id="lkw_0_80" depart="1531.91" type="truck_truck" departLane="best" departSpeed="max" departPos="random">
        <route edges="-53175159#3 -53175159#1 53175164#0 53175164#2 188462504 150697171#1 319999605#1 319999605#4 319999605#5 319999605#6 319999605#7 4084169 53040717 323709010 323709011#0 323709011#2 323709012#0 323709012#1 25876774 25876775#0 25876775#1 181337671#0 280873233 181337547 181336338 396385838 181337215 188324464 102526743#0 102526743#2 144934063 144932088#0 152412638#0 152412638#1 171569487 181332523#0 181332523#1 181332523#2 181332526 426912948#0 426912948#1 426912948#2 426912948#5 426452841#0 383597641#0 383597641#2 383597641#3 383597641#4 383597641#5 383597641#6 190053109#0 190053109#1 -190053109#2"/>
    </vehicle>
    <vehicle id="lkw_0_81" depart="1551.06" type="truck_truck" departLane="best" departSpeed="max" departPos="random">
        <route edges="150770619#1 -238870176#3 -238870176#2 -238870176#0 -205190519 23567307 269040918 251106111#0 189032454 269040914 150770614#1 33083535#0"/>
    </vehicle>
    <vehicle id="lkw_0_82" depart="1570.21" type="truck_truck" departLane="best" departSpeed="max" departPos="random">
        <route edges="35268174#2 -57381283#1 57381283#1 35268175 204648992#0 204648992#1 204648992#3 175204223#0 175204223#1 175204223#2 4084172 114389127#1 114389127#2 114389127#3 114389127#4 377905808#0 377905808#2 377905809#2 377905809#3 377905809#4 269017600#0 269017600#1 163419805#0 163419805#1 163419805#2 163419466#0 163419466#1 163419466#3 163419466#4 163419466#7 185352101 150697171#1 319999605#1 319999605#4 319999605#5 319999605#6 319999605#7 4084169 53040717 323709010 323709011#0 323709011#2 323709012#0 323709012#1 25876774 25876775#0 25876775#1 181337671#0 280873233 181337547 181336338 396385838 181337215 188324464 102526743#0 102526743#2 144934063 144932088#0 152412638#0 152412638#1 171569487 181332523#0 181332523#1 181332523#2 181332526 426912948#0 426912948#1 426912948#2 426912948#5 426452841#0 383597641#0 383597641#2 383597641#3 383597641#4 383597641#5 383597641#6 190053109#0 190053109#1 190053109#3 190053109#4 190053109#5 204526318#1 204526318#2 204526318#3 204526318#5 204526318#6"/>
    </vehicle>
    <vehicle id="lkw_0_83" depart="1589.36" type="truck_truck" departLane="best" departSpeed="max" departPos="random">
        <route edges="366073486 282331232#0 282331232#1 149888264#1 203461111 -238870176#3 -238870176#2 -238870176#0 -205190519 23567307 269040918 251106111#0 189032454 269040914 385970249#2 385970249#3 305792174#2"/>
    </vehicle>
    <vehicle id="lkw_0_84" depart="1608.51" type="truck_truck" departLane="best" departSpeed="max" departPos="random">
        <route edges="19354458#0 19354458#1 19354458#2 150546879#0 150546879#1 19354456 442789059 179527904#1 508099915#0 508099915#1 258979265#0 258979265#1 628505597 165849631 387015278 251098655#0 -43578399#4 -43578399#2 -43578399#1 -43578399#0 189877848 96747828#0 96747828#1 56185651#3 251161934#0 226991208#0 228126461#1 462537200#1 161847018#1 432348155 404599857#0 404599857#1 404599857#2 23055466#0"/>
    </vehicle>
    <vehicle id="lkw_0_85" depart="1627.66" type="truck_truck" departLane="best" departSpeed="max" departPos="random">
        <route edges="-502060954 -502060955#1 -502060955#0 -150697173#1 -150697173#0 366073489#3 366073490#1 366073490#2 366073490#3 230602997#0 230602997#1 230602997#2 24666916 366073460#1 366073459#0 189032454 269040914 150770614#1 -332237966 332237966"/>
    </vehicle>
    <vehicle id="lkw_0_86" depart="1646.81" type="truck_truck" departLane="best" departSpeed="max" departPos="random">
        <route edges="-502060954 -502060955#1 -502060955#0 -150697173#1 -150697173#0 366073489#3 366073490#1 366073490#2 366073490#3 230602997#0 230602997#1 230602997#2 24666916 366073460#1 366073459#0 189032454 269040914 150770614#1 -332237966 332237966"/>
    </vehicle>
    <vehicle id="lkw_0_87" depart="1665.96" type="truck_truck" departLane="best" departSpeed="max" departPos="random">
        <route edges="53175159#12 -53175159#12 24549661#0 24549661#1 -208426933#2 24608208#0 24608208#1 163419466#3 163419466#4 163419466#7 185352101 150697171#1 319999605#1 319999605#4 319999605#5 319999605#6 319999605#7 4084169 53040717 323709010 323709011#0 323709011#2 323709012#0 323709012#1 25876774 25876775#0 25876775#1 181337671#0 280873233 181337547 181336338 396385838 181337215 188324464 188324465#0 188324465#2 188324465#3 360073480 100302818#1 100302818#2 100302818#3"/>
    </vehicle>
    <vehicle id="lkw_0_88" depart="1685.11" type="truck_truck" departLane="best" departSpeed="max" departPos="random">
        <route edges="334457597#0 -334457597#0 -334457596 -334457598#4 -334457598#3 -334457598#0 -134394675#4 -134394675#3 -134394675#2 -134394675#1 -134394675#0 134394171#3 323709012#0 323709012#1 25876774 25876775#0 25876775#1 181337671#0 280873233 181337547 181336338 396385838 181337215 188324464 102526743#0 102526743#2 144934063 144932088#0 152412638#0 152412638#1 171569487 181332523#0 181332523#1 181332523#2 181332526 426912948#0 426912948#1 426912948#2 426912948#5 426452841#0 383597641#0 383597641#2 383597641#3 383597641#4 383597641#5 383597641#6 190053109#0 190053109#1 190053109#3 25851182#0 25851182#1 25851182#2 25851182#3"/>
    </vehicle>
    <vehicle id="lkw_0_89" depart="1704.26" type="truck_truck" departLane="best" departSpeed="max" departPos="random">
        <route edges="203461111 203461112#1 230602993 190438083#0 190438083#1 269040907#0 269040907#1 204400292 251109201 187060050#2 781345962 300035524 150857432#2 93785423 253488957#0 94586305 500261498 94586298 500261497 150837582#1 150837582#2 150837582#3 185579896#0 185579896#1 95170297#0 53175060#0 53175060#1 24549659 97142258 53175159#9 53175159#10 53175159#11"/>
    </vehicle>
    <vehicle id="lkw_0_90" depart="1723.40" type="truck_truck" departLane="best" departSpeed="max" departPos="random">
        <route edges="150554193#0 28874733#0 190431168#2 227062818#1 227062818#3 227062818#4 227062813#0 227062813#1 227062813#2 227062813#3 258979261 255391114#0 475679571#0 475679571#1 475679571#2 475679571#3 402016820#0 187060058#0 187060058#3 187060057#0 42760132 371300204#0 -150549252#2 150549252#2"/>
    </vehicle>
    <vehicle id="lkw_0_91" depart="1742.55" type="truck_truck" departLane="best" departSpeed="max" departPos="random">
        <route edges="150554195#2 150554195#3 258979269#1 227062818#1 227062818#3 227062818#4 227062813#0 227062813#1 227062813#2 227062813#3 258979261 255391114#0 475679571#0 475679571#1 475679571#2 475679571#3 402016820#0 187060058#0 187060058#3 187060057#0 42760132 371300204#0 35834153#0 -150549249#0"/>
    </vehicle>
    <vehicle id="lkw_0_92" depart="1761.70" type="truck_truck" departLane="best" departSpeed="max" departPos="random">
        <route edges="376865290#1 300034825 472148300 867790499#1 253488980 253488984 149899046 204400292 251109201 187060050#2 781345962 300035524 150857432#2 93785423 253488957#0 94586305 500261498 94586298 500261497 150837582#1 150837582#2 150837582#3 185579896#0 185579896#1 53175059#1 53175059#2 187061084 93785463#0 93785463#1 190458990#0 190458990#2 151788685 269017597#0 269017597#1 269017597#2 269017597#3 269017597#4 269017597#5 269017597#6 190458063 190458064#2 190458064#3 190458064#4 114389127#2 114389127#3 114389127#4"/>
    </vehicle>
    <vehicle id="lkw_0_93" depart="1780.85" type="truck_truck" departLane="best" departSpeed="max" departPos="random">
        <route edges="246584302#0 246584302#2 500582850 500582851#1 255389622#0 255389622#3 255389622#4 255389622#5 255389622#6 255389622#8 255389622#9 255389621#0 255389621#1 255389621#2 255389621#3 165849626 165849630#0 150551277#2 363826076 628505596 190431168#1 190431168#2 227062818#1 227062818#3 227062818#4 227062813#0 227062813#1 227062813#2 227062813#3 258979261 255391114#0 475679571#0 475679571#1 475679571#2 475679571#3 402016820#0 187060058#0 187060058#3 187060057#0 42760132 371300204#0 190032739 371300202 40584785#0 40584784"/>
    </vehicle>
<!-- begin="1800.0" end="3600.0" -->
    <vehicle id="lkw_1800_0" depart="1800.00" type="truck_truck" departLane="best" departSpeed="max" departPos="random">
        <route edges="402016765 24377457 85287424 85287423#0 187060058#0 187060058#3 187060057#0 42760132 85270645 320185351 320185500#0 320185500#1 320185500#3 270655640 270655641 189899508 360065008 268931669 268931672#0 268931670 268931671 4235244 204207303#0 164095588#2 204207294 45085545 5097800 4181088 204207292 178229026#1 178225533 178225534 18694413 178226651#1 305390361#2 305390361#3 24599109 -25548343#4"/>
    </vehicle>
    <vehicle id="lkw_1800_1" depart="1833.33" type="truck_truck" departLane="best" departSpeed="max" departPos="random">
        <route edges="-43578399#2 150556234#1 165823636 227062816 165828294#0 581663849 360248203#1 360248191 360248194 360248197#0 360248197#1 360248209#1 268931670 268931671 4235244"/>
    </vehicle>
    <vehicle id="lkw_1800_2" depart="1866.67" type="truck_truck" departLane="best" departSpeed="max" departPos="random">
        <route edges="178206109#0 178206109#1 178205027 204207289 18695339#0 178229025#5 204207291 5097799"/>
    </vehicle>
    <vehicle id="lkw_1800_3" depart="1900.00" type="truck_truck" departLane="best" departSpeed="max" departPos="random">
        <route edges="178206109#0 178206109#1 178205027 204207289 18695339#0 178229025#5 204207291 5097799"/>
    </vehicle>
    <vehicle id="lkw_1800_4" depart="1933.33" type="truck_truck" departLane="best" departSpeed="max" departPos="random">
        <route edges="46963653#0 -46963653#0 150393270#12 121805107#0 121805107#1 121805107#2 32280972#5 32280972#0 32280972#1 121805100 189889903#0 189889903#1 -150393273#3 -150393273#1 -150393273#0 -360787852#3 -360787852#2 -360787852#0 -5475488#1 190340312 216879571 674280493 102774826 102749569 4474685 24377358 85287424 85287423#0 187060058#0 187060058#3 187060057#0 42760132 85270645 320185351 320185500#0 320185500#1 320185500#3 270655640 270655641 189899508 360065008 268931669 268931672#0 268931670 268931671 4235244 204207303#0 164095588#2 305325048#0 305325046 305325049#0 305325049#1 305325049#2 236994807 5073592#0 5073592#2 5073592#3 5073592#4 5073592#5 692648169#0 123555933#0 123555933#1 123555933#2 269001612#2 269001612#3 269001612#4 269001612#5"/>
    </vehicle>
    <vehicle id="lkw_1800_5" depart="1966.67" type="truck_truck" departLane="best" departSpeed="max" departPos="random">
        <route edges="24599111#2 -24599111#2 -24598648#3 -24598648#2 -24598648#1 -24598648#0 181336164#3 181336164#4 181336164#5 181336164#6 181336164#7 78489606 178235948#0 178235948#1 178235035 178226533#0 178226496 301704185#0 178229025#5 204207291 5097799 4235242#0 164086589 164086593 45085542#0 268931673#1 270655631 270655638 220911179 189899976 561882213#0 561882213#1 320185059 85270645 320185351 320185500#0 320185500#1"/>
    </vehicle>
    <vehicle id="lkw_1800_6" depart="2000.00" type="truck_truck" departLane="best" departSpeed="max" departPos="random">
        <route edges="366073475#1 -38152916#0 -150851814#6 -150851814#5 -150851814#4 33083418#0 33083418#2 190443836#2 190443836#4 189769943#0 269040917 127607225#2 154656276#2 -35948955#1 -35948955#0 -238870176#2 -238870176#0 -205190519 251102622#0 251102622#1 251102620"/>
    </vehicle>
    <vehicle id="lkw_1800_7" depart="2033.33" type="truck_truck" departLane="best" departSpeed="max" departPos="random">
        <route edges="253488948 253488950#0 112562464 46967473 502060953#0 502060953#1 182065983#1 246584302#0 246584302#2 500582850 500582851#1 255389622#0 255389622#3 255389622#4 255389622#5 255389622#6 255389622#8 255389622#9 255389621#0 255389621#1 255389621#2 255389621#3 165849626 165849630#0 150551277#2 363826076 628505596 360248203#1 360248191 360248194"/>
    </vehicle>
    <vehicle id="lkw_1800_8" depart="2066.67" type="truck_truck" departLane="best" departSpeed="max" departPos="random">
        <route edges="-18314329#1 18314329#1 43795168#4 43795168#5 43795168#6 43795168#7 43795168#8 194765169#2 43792812#1 43792812#2 -518809865#1 -518809865#0 43793038#1 360072943#0 360072943#1 258979231#0 258979231#1 144932611 144932612 252753975#1 181335262 293281410#0 144916662 181336164#0 181336164#1 181336164#2 181336164#3 181336164#4 181336164#5 181336164#6 181336164#7 78489606 178235948#0 178235948#1 178235035 178226533#0 178226496 301704185#0 178229025#5 204207291 5097799 4235242#0 164086589 164086593 45085542#0 268931673#1 270655631 270655638 220911179 189899976 561882213#0 561882213#1 320185059 190022224#1 115738329#0 29350090 320202776 150546874#1 320210276 320210275 320221191 56185655#0 56185655#1 189776524 56454445 187057791#0 187057791#1 187057791#2 471554672 184227241#0 184227241#1 184227241#2 360788356 371573875 371573874 371573876#0 371573876#1 371573876#2 371573876#3 -371573876#3"/>
    </vehicle>
    <vehicle id="lkw_1800_9" depart="2100.00" type="truck_truck" departLane="best" departSpeed="max" departPos="random">
        <route edges="24377361 -104363155#1 24377359 56185654 56185655#0 56185655#1 189776524 56454445 187057791#0 187057791#1 187057791#2 471554672 184227241#0 184227241#1 184227241#2 184227241#4 292947985 150395822 25589596 27134171 14189055 5111817 26408353 114976950 74539230#0 74539230#1 225198733#0 251327592#1 77122439#0 77122439#1 -77122446#3 -77122446#2 -77122446#1 -77122446#0 -30163590#4 -30163590#3 -30163590#2 -30163590#1 -30163590#0 -625333807#1 -625333807#0 -50916530#4 -50916530#3 -50916530#2 -50916530#1 -50916530#0 -870453325 -50919061#3 -50919061#2 -50919061#1 -50919061#0 -749003346 -206233781#0"/>
    </vehicle>
    <vehicle id="lkw_1800_10" depart="2133.33" type="truck_truck" departLane="best" departSpeed="max" departPos="random">
        <route edges="27429649 753460698 25891699 359948072 184156818 184156828 56185654 56185655#0 56185655#1 189776524 56454445 187057791#0 187057791#1 187057791#2 471554672 184227241#0 184227241#1 184227241#2 184227241#4 292947985 150395822 25589596 27134171 14189055 5111817 26408353 114976950 74539230#0 74539230#1 225198733#0 251327592#1 77122439#0 77122439#1 480590963#0 480590963#1 480590961 480590958 480590956 77122422#1 77122422#2 480590954 -749288423#0 -749288422 749288422"/>
    </vehicle>
    <vehicle id="lkw_1800_11" depart="2166.67" type="truck_truck" departLane="best" departSpeed="max" departPos="random">
        <route edges="4404113#3 268931687 376865405#3 376865390#1 268931678 268931683#1 305325048#0 305325046 305325049#0 305325049#1 305325049#2 236994807 236994808 252024823#0 252024823#2 268931656 236995001 268931659#0 4084166 268931652 188466506 268931675#1 268931675#2 27261757#2 27261757#3 262140928 28297618#0 -28297618#0 -262140928"/>
    </vehicle>
    <vehicle id="lkw_1800_12" depart="2200.00" type="truck_truck" departLane="best" departSpeed="max" departPos="random">
        <route edges="320239489#0 320237745 320252264 265910769 320252634#1 320252634#2 -27283179#1 -27283179#0 320202776 475679571#0 475679571#1 475679571#2 475679571#3 402016820#0 187060058#0 187060058#3 187060057#0 42760132 85270645 320185351 320185500#0 320185500#1 320185500#3 270655640 270655641 189899508 360065008 268931669 268931672#0 268931670 268931671 4235244 204207303#0 164095588#2 305325048#0 659292418#1 659292417#0"/>
    </vehicle>
    <vehicle id="lkw_1800_13" depart="2233.33" type="truck_truck" departLane="best" departSpeed="max" departPos="random">
        <route edges="442749531 442749533 183654631 23263282 235390974 235391021 235391020#0 235391020#1 235391022 396381365 235389907 235389906 235389908#0 269001612#2 269001612#3 269001612#4 269001612#5 235390248#0 235390248#1 305325046 305325049#0 305325049#1 305325049#2 236994807 236994808 252024823#0 252024823#2 268931656 236995001 268931659#0 4084166 268931652 190347317#0 187060053#0 42760134 187060055 53175058 315426058#1 315426061 315426063 315426062 150000852 150000376#2 189773010#0 189773010#1 149996793 190451914#1"/>
    </vehicle>
    <vehicle id="lkw_1800_14" depart="2266.67" type="truck_truck" departLane="best" departSpeed="max" departPos="random">
        <route edges="442749531 442749533 183654631 23263282 235390974 235391021 235391020#0 235391020#1 235391022 396381365 235389907 235389906 235389908#0 269001612#2 269001612#3 269001612#4 269001612#5 235390248#0 235390248#1 305325046 305325049#0 305325049#1 305325049#2 236994807 236994808 252024823#0 252024823#2 268931656 236995001 268931659#0 4084166 268931652 190347317#0 187060053#0 42760134 187060055 53175058 315426058#1 315426061 315426063 315426062 150000852 150000376#2 189773010#0 189773010#1 149996793 190451914#1"/>
    </vehicle>
    <vehicle id="lkw_1800_15" depart="2300.00" type="truck_truck" departLane="best" departSpeed="max" departPos="random">
        <route edges="190443836#2 190443836#4 189769943#0 150770614#1 33083535#0 33083535#1 366073462#0 366073462#1 366073461 208424705#0 -366073490#3 -366073490#2 -366073490#1 -366073490#0 -366073489#2 -366073489#1 -366073489#0 -40521205#0 -431557291 -40521208#1 404190177 -24534083#3 -24534083#2 -24534083#1 -24534083#0"/>
    </vehicle>
    <vehicle id="lkw_1800_16" depart="2333.33" type="truck_truck" departLane="best" departSpeed="max" departPos="random">
        <route edges="28560402#1 -28560402#1 -28560402#0 791260171 -870453326 -28560406#1 -28560406#0 -229460712#1 -229460712#0 25948331 516863395#0 516863395#1 258194205 150398308 456934817 184156805 150398305 8611964 184156816 184156815 5466445#0 190340312 216879571 674280493 150546872 181503326#0 181503326#1 255392314 255392313#0 387015286 409702806#1 438279356 -150546877#2 -150546877#1 -150546877#0 150546877#0"/>
    </vehicle>
    <vehicle id="lkw_1800_17" depart="2366.67" type="truck_truck" departLane="best" departSpeed="max" departPos="random">
        <route edges="37811442#0 37811442#2 387015289#0 387015289#1 165849627#5 165849627#6 165849627#7 165849627#8 165849627#9 376865290#0 376865290#1 300034825 472148300 867790499#1 253488980 149898017#0 150000852 150000376#2 189773010#0 189773010#1 149996793 9040997 251158323 251158324#1 161847017 433018233#0 433018233#1 433018233#2 114198529 191128494 385966809#0"/>
    </vehicle>
    <vehicle id="lkw_1800_18" depart="2400.00" type="truck_truck" departLane="best" departSpeed="max" departPos="random">
        <route edges="27429649 753460698 25891699 359948072 184156818 184156828 56185654 56185655#0 56185655#1 189776524 56454445 187057791#0 187057791#1 187057791#2 471554672 184227241#0 184227241#1 184227241#2 184227241#4 292947985 150395822 25589596 27134171 14189055 5111817 26408353 114976950 74539230#0 74539230#1 225198733#0 251327592#1 77122439#0 77122439#1 480590963#0 480590963#1 480590961 480590958 480590956 77122422#1 77122422#2 480590954 -749288423#0 -749288422 749288422"/>
    </vehicle>
    <vehicle id="lkw_1800_19" depart="2433.33" type="truck_truck" departLane="best" departSpeed="max" departPos="random">
        <route edges="27429649 753460698 25891699 359948072 184156818 184156828 56185654 56185655#0 56185655#1 189776524 56454445 187057791#0 187057791#1 187057791#2 471554672 184227241#0 184227241#1 184227241#2 184227241#4 292947985 150395822 25589596 27134171 14189055 5111817 26408353 114976950 74539230#0 74539230#1 225198733#0 251327592#1 77122439#0 77122439#1 480590963#0 480590963#1 480590961 480590958 480590956 77122422#1 77122422#2 480590954 -749288423#0 -749288422 749288422"/>
    </vehicle>
    <vehicle id="lkw_1800_20" depart="2466.67" type="truck_truck" departLane="best" departSpeed="max" departPos="random">
        <route edges="187060049#1 561882212 115738329#0 29350090 320202776 150546874#1 320210276 320210275 320221191 56185655#0 56185655#1 189776524 56454445 187057791#0 187057791#1 187057791#2 23137790#2 150543795 56186952#0 56186952#1 35134167#0 35134167#2 35134167#3 276412885 276412658 189877634#0 96747828#0 96747828#1 56185651#3 251161934#0 226991208#0 228126461#1 462537200#1 249375697#1 433018231 433018232 269040901#0 269040901#1 189772874#0 190451914#1 251106575 251106198#0 251106198#2 205190519 238870176#0 238870176#2 35948955#0 35948955#1 -35948955#1"/>
    </vehicle>
    <vehicle id="lkw_1800_21" depart="2500.00" type="truck_truck" departLane="best" departSpeed="max" departPos="random">
        <route edges="190443836#0 190443836#2 190443836#4 189769943#0 385970249#2 385970249#3 305792174#2 305792174#3 305792174#4 249599484#0 249599484#1 -249599484#1"/>
    </vehicle>
    <vehicle id="lkw_1800_22" depart="2533.33" type="truck_truck" departLane="best" departSpeed="max" departPos="random">
        <route edges="24534243#0 24534243#1 262140928 28297618#0 28297618#1 502060953#0 502060953#1 182065983#1 53175058 315426058#1 315426061 315426063 315426062 150000852 150000376#2 189773010#0 189773010#1 149996793 9040997 251158323 251158324#1 251158322#0 548514765 228126460#0 316778911#0 287186149#1 251161865#1 781419324 404599852 404599853 251157594 548514764#2 548514763#0 189876499 160173625 360785921#0 360785921#1 5111851 360785920#0 190340308 399741814#0 399741814#1 190340307 399741671 471554672 184227241#0 184227241#1 184227241#2 360788356 -360788356"/>
    </vehicle>
    <vehicle id="lkw_1800_23" depart="2566.67" type="truck_truck" departLane="best" departSpeed="max" departPos="random">
        <route edges="4082105 753460698 25891699 359948072 184156818 184156828 56185654 56185655#0 56185655#1 189776524 56454445 187057791#0 187057791#1 187057791#2 23137790#2 150543795 56186952#0 56186952#1 35134167#0 35134167#2 35134167#3 276412885 276412658 189877634#0 96747828#0 96747828#1 56185651#3 251161934#0 226991208#0 228126461#1 462537200#1 249375697#1 433018231 433018232 269040901#0 269040901#1 189772874#0 190451409 269040904 150770619#1 150770619#4 24725160#0 24725160#1 149888267 149888264#1"/>
    </vehicle>
    <vehicle id="lkw_1800_24" depart="2600.00" type="truck_truck" departLane="best" departSpeed="max" departPos="random">
        <route edges="150547351#0 150547351#1 150547351#2 150549253#4 320185059 190022224#1 115738329#0 29350090 320202776 150546874#1 320210276 320210275 320221191 56185655#0 56185655#1 189776524 56454445 187057791#0 187057791#1 187057791#2 471554672 184227241#0 184227241#1 184227241#2 184227241#4 292947985 150395822 25589596 27134171 14189055 5111817 26408353 114976950 74539230#0 74539230#1 225198733#0 251327592#1 77122439#0 77122439#1 -77122446#3 -77122446#2 -77122446#1 -77122446#0 -30163590#4 -30163590#3 -30163590#2 -30163590#1 -30163590#0 -625333807#1 -625333807#0 -50916530#4 -50916530#3 -50916530#2 -50916530#1 -50916530#0 -870453325 -50919061#3 -50919061#2 -50919061#1 -50919061#0 -229460712#1 -229460712#0 25948331 516863395#0 516863395#1 258194205 150398308 456934817 184156805 150398305 8611964 184156816 184156815"/>
    </vehicle>
    <vehicle id="lkw_1800_25" depart="2633.33" type="truck_truck" departLane="best" departSpeed="max" departPos="random">
        <route edges="255389622#4 255389622#5 255389622#6 255389622#8 255389622#9 255389621#0 255389621#1 255389621#2 255389621#3 165849626 4404113#0 4404113#1 4404113#3 268931687 376865405#3 376865390#1 268931678 268931683#1 204207294 150549933#0 164086589 164086593 45085542#0 268931673#1 270655631 270655638 220911179 189899976 47214334#0 47214334#2 47214334#3"/>
    </vehicle>
    <vehicle id="lkw_1800_26" depart="2666.67" type="truck_truck" departLane="best" departSpeed="max" departPos="random">
        <route edges="189899508 360065008 268931669 268931672#0 268931670 268931671 4235244 204207303#0 164095588#2 305325048#0 305325046 305325049#0 305325049#1 305325049#2 236994807 5073592#0 5073592#2 5073592#3 5073592#4 5073592#5 14103491#0 251987384#0 251987384#1 251987384#2 251987384#3 269001615#1 235391298 237023442#0 269001613#0 269001613#1 176570669#1 185573957#0 150663777 -319999605#7 -319999605#6 -319999605#5 -319999605#4 -319999605#1 -94586280#3 -94586280#2 -94586280#1 -94586280#0 -502060954"/>
    </vehicle>
    <vehicle id="lkw_1800_27" depart="2700.00" type="truck_truck" departLane="best" departSpeed="max" departPos="random">
        <route edges="253488948 253488950#0 112562464 46967473 502060953#0 502060953#1 182065983#1 246584302#0 246584302#2 500582850 500582851#1 255389622#0 255389622#3 255389622#4 255389622#5 255389622#6 255389622#8 255389622#9 255389621#0 255389621#1 255389621#2 255389621#3 165849626 165849630#0 150551277#2 363826076 628505596 360248203#1 360248191 360248194"/>
    </vehicle>
    <vehicle id="lkw_1800_28" depart="2733.33" type="truck_truck" departLane="best" departSpeed="max" departPos="random">
        <route edges="-238870175#0 -249599484#3 -249599484#2 -249599484#1 -249599484#0 -305792174#4 -305792174#3 -305792174#2 -385970249#3 -385970249#2 269040917 127607225#2 127607225#3 127607225#5 23567306#0 23567306#1 23567306#2 269040899 190451409 269040904 230602993 190438083#0 190438083#1 269040907#0 269040907#1 149899941 253488977#0 42760138 187060052 149904354 218778912 268931658 188466506 268931675#1"/>
    </vehicle>
    <vehicle id="lkw_1800_29" depart="2766.67" type="truck_truck" departLane="best" departSpeed="max" departPos="random">
        <route edges="27429649 753460698 25891699 359948072 184156818 184156828 56185654 56185655#0 56185655#1 189776524 56454445 187057791#0 187057791#1 187057791#2 471554672 184227241#0 184227241#1 184227241#2 184227241#4 292947985 150395822 25589596 27134171 14189055 5111817 26408353 114976950 74539230#0 74539230#1 225198733#0 251327592#1 77122439#0 77122439#1 480590963#0 480590963#1 480590961 480590958 480590956 77122422#1 77122422#2 480590954 -749288423#0 -749288422 749288422"/>
    </vehicle>
    <vehicle id="lkw_1800_30" depart="2800.00" type="truck_truck" departLane="best" departSpeed="max" departPos="random">
        <route edges="-208426933#2 24608208#0 24608208#1 163419466#3 163419466#4 163419466#7 185352101 150697171#1 319999605#1 319999605#4 319999605#5 319999605#6 319999605#7 4084169 150663777 185573958 237278283 237278282#3 268931664#1 268931665 147683978#0 4084166 4432606#1 4432606#2 4432606#3 4432606#4 4432606#5 4432606#6 4432606#8 4432606#9 4432606#10"/>
    </vehicle>
    <vehicle id="lkw_1800_31" depart="2833.33" type="truck_truck" departLane="best" departSpeed="max" departPos="random">
        <route edges="-238870175#0 -249599484#3 -249599484#2 -249599484#1 -249599484#0 -305792174#4 -305792174#3 -305792174#2 -385970249#3 -385970249#2 269040917 127607225#2 127607225#3 127607225#5 23567306#0 23567306#1 23567306#2 269040899 190451409 269040904 230602993 190438083#0 190438083#1 269040907#0 269040907#1 149899941 253488977#0 42760138 187060052 149904354 218778912 268931658 42760136 268931654#1 42760135#0 42760135#2 42760135#3 880134845 305869959#1 4084169 53040717 323709010 323709011#0 323709011#2 323709012#0 323709012#1 25876774 25876775#0 25876775#1 181337671#0 280873233 181337547 181336338 144918027#1 144918027#2 144918027#3 461562479#0 461562479#2 461562478#1 426912946#0"/>
    </vehicle>
    <vehicle id="lkw_1800_32" depart="2866.67" type="truck_truck" departLane="best" departSpeed="max" departPos="random">
        <route edges="-43578399#2 150556234#1 165823636 227062816 165828294#0 581663849 360248203#1 360248191 360248194 360248197#0 360248197#1 360248209#1 268931670 268931671 4235244"/>
    </vehicle>
    <vehicle id="lkw_1800_33" depart="2900.00" type="truck_truck" departLane="best" departSpeed="max" departPos="random">
        <route edges="402016765 24377457 85287424 85287423#0 187060058#0 187060058#3 187060057#0 42760132 85270645 320185351 320185500#0 320185500#1 320185500#3 270655640 270655641 189899508 360065008 268931669 268931672#0 268931670 268931671 4235244 204207303#0 164095588#2 204207294 45085545 5097800 4181088 204207292 178229026#1 178225533 178225534 18694413 178226651#1 305390361#2 305390361#3 24599109 -25548343#4"/>
    </vehicle>
    <vehicle id="lkw_1800_34" depart="2933.33" type="truck_truck" departLane="best" departSpeed="max" departPos="random">
        <route edges="188324465#0 188324465#2 188324465#3 360073480 360072943#0 360072943#1 258979231#0 258979231#1 144932611 144932612 252753975#1 181335262 293281410#0 258979178#1 251066998 251066997#0 101617775#0 101617775#1 101617775#2 5182256 24909171 251065565 176570669#1 185573957#0 150663777 185573958 237278283 237278282#3 268931664#1 268931665 147683978#0 4084166 4432606#1 4432606#2 4432606#3 4432606#4"/>
    </vehicle>
    <vehicle id="lkw_1800_35" depart="2966.67" type="truck_truck" departLane="best" departSpeed="max" departPos="random">
        <route edges="23055466#0 23055466#1 23055466#3 23055466#4 23055466#5 299639054 376865290#0 376865290#1 300034825 472148300 867790499#1 253488980 253488984 149899046 149899941 253488977#0 42760138 187060052 149904354 218778912 268931658 42760136 268931654#1 42760135#0 42760135#2 42760135#3 880134845 305869959#1 4084169 53040717 323709010 323709011#0 323709011#2 323709012#0 323709012#1 25876774 25876775#0 25876775#1 181337671#0 280873233 181337547 181336338 144918027#1 144918027#2 144918027#3 461562479#0 461562479#2 -171509379 -189575384#8 147249981#0 147249981#1 -147249981#1"/>
    </vehicle>
    <vehicle id="lkw_1800_36" depart="3000.00" type="truck_truck" departLane="best" departSpeed="max" departPos="random">
        <route edges="867790499#1 253488980 149898017#0 150000852 150000376#2 189773010#0 189773010#1 149996793 9040997 251158323 251158324#1 251158322#0 548514765 228126460#0 316778911#0 287186149#1 251161865#1 781419324 404599852 404599853 251157594 548514764#2 548514763#0 189876499 160173625 360785921#0 360785921#1 5111851 360785920#0 190340308 399741814#0 399741814#1 190340307 399741671 5475488#1 360787852#0 360787852#2 360787852#3 150393273#0 150393273#1 150393273#3 121805095 32280972#3"/>
    </vehicle>
    <vehicle id="lkw_1800_37" depart="3033.33" type="truck_truck" departLane="best" departSpeed="max" departPos="random">
        <route edges="753460698 25891699 359948072 184156818 184156828 56185654 56185655#0 56185655#1 189776524 56454445 187057791#0 187057791#1 187057791#2 23137790#2 150543795 56186952#0 56186952#1 35134167#0 35134167#2 35134167#3 276412885 276412658 189877634#0 96747828#0 96747828#1 56185651#3 251161934#0 226991208#0 228126461#1 462537200#1 249375697#1 433018231 433018232 269040901#0 269040901#1 189772874#0 190451409 269040904 230602993 190438083#0 190438083#1 269040907#0 269040907#1 204400292 251109201 187060050#2 781345962 -313209997#2 313209997#2"/>
    </vehicle>
    <vehicle id="lkw_1800_38" depart="3066.67" type="truck_truck" departLane="best" departSpeed="max" departPos="random">
        <route edges="165849627#1 165849627#2 165849627#3 165849627#5 165849627#6 165849627#7 165849627#8 165849627#9 376865290#0 376865290#1 300034825 472148300 867790499#1 253488980 149898017#0 150000852 150000376#2 189773010#0 189773010#1 149996793 190451409"/>
    </vehicle>
    <vehicle id="lkw_1800_39" depart="3100.00" type="truck_truck" departLane="best" departSpeed="max" departPos="random">
        <route edges="-190340311 -182489863 -229917857#1 35834154 182489865 688370155 320185839#0 320185351 320185500#0 320185500#1 320185500#3 270655640 270655641 189899508 360065008 268931669 268931672#0 268931670 268931671 4235244 204207303#0 164095588#2 305325048#0 305325046 305325049#0 305325049#1 305325049#2 236994807 5073592#0 5073592#2 5073592#3 5073592#4 5073592#5 14103491#0 251987384#0 251987384#1 251987384#2 251987384#3 269001615#1 235391298 150694607#0 150694607#2 183654500#0"/>
    </vehicle>
    <vehicle id="lkw_1800_40" depart="3133.33" type="truck_truck" departLane="best" departSpeed="max" departPos="random">
        <route edges="178206109#0 178206109#1 178205027 204207289 18695339#0 178229025#5 204207291 5097799"/>
    </vehicle>
    <vehicle id="lkw_1800_41" depart="3166.67" type="truck_truck" departLane="best" departSpeed="max" departPos="random">
        <route edges="35014371#4 -35014371#4 -35014371#3 -35014371#0 739924927#0 739924927#2 240321454#2 38142471 38139887#0 38139887#1 -360787852#3 -360787852#2 -360787852#0 -5475488#1 23137790#2 150543795 56186952#0 56186952#1 35134167#0 35134167#2 35134167#3 276412885 276412658 165825876 191003931#0 191003931#1 227062816 165828294#0 -150554195#1"/>
    </vehicle>
    <vehicle id="lkw_1800_42" depart="3200.00" type="truck_truck" departLane="best" departSpeed="max" departPos="random">
        <route edges="-7980450#1 4432606#8 4432606#9 4432606#10 4404113#3 268931687 376865405#3 376865390#1 268931678 268931683#1 204207294 45085545 5097800 4181088 204207292 178229026#1 178225533 305379130#0 204207308 305325054#2 152378956#0 152378956#1 152378956#2 152378956#3 152378956#4 152378956#5 204207290#0 204207290#1 204207290#4 267411640#0 267411640#2 178205026 -598189702#1 -178206109#0 -778957164#1 -778957164#0 -520753136#1 -25878783#2"/>
    </vehicle>
    <vehicle id="lkw_1800_43" depart="3233.33" type="truck_truck" departLane="best" departSpeed="max" departPos="random">
        <route edges="150554198#7 150554193#0 150554193#1 360248191 360248194 360248197#0 360248197#1 360248209#1 268931670 268931671 4235244 204207303#0 164095588#2 305325048#0 305325046 305325049#0 305325049#1 305325049#2 236994807 5073592#0 5073592#2 5073592#3 5073592#4 5073592#5 14103491#0 251987384#0 251987384#1 251987384#2 251987384#3 269001615#1 235391298 150694607#0 150694607#2 183654500#0 183654500#1 183654224 -269017585 -442749533 -442749531 -269017588#4 -269017588#3 -269017588#1 -269017588#0 -532149775#2 -532149775#1 -27287268"/>
    </vehicle>
    <vehicle id="lkw_1800_44" depart="3266.67" type="truck_truck" departLane="best" departSpeed="max" departPos="random">
        <route edges="502060953#1 182065983#1 246584302#0 246584302#2 500582850 500582851#1 255389622#0 255389622#3 255389622#4 255389622#5 255389622#6 255389622#8 255389622#9 255389621#0 255389621#1 255389621#2 255389621#3 165849626 165849630#0 150551277#2 363826076 628505596 190431168#1 190431168#2 227062818#1 360248187#3 360248187#4 360248187#5 360248187#6 360248187#7 28143931#0 28143931#1 227062814 227062815#0 227062815#1 19354458#0 19354458#1 19354458#2 150546879#0 150546879#1"/>
    </vehicle>
    <vehicle id="lkw_1800_45" depart="3300.00" type="truck_truck" departLane="best" departSpeed="max" departPos="random">
        <route edges="35773267#1 35773267#2 -74153950 74046358 28462311#0 480583011#1 286708821 480583010#0 286708819 127170001#0 127170001#1 127170001#2 74539230#0 74539230#1 225198733#0 251327592#1 77122439#0 77122439#1 -77122446#3 -77122446#2 -77122446#1 -77122446#0 -30163590#4 -30163590#3 -30163590#2 -30163590#1 -30163590#0 -625333807#1 -625333807#0 -50916530#4 -50916530#3 -50916530#2 -50916530#1 -50916530#0 -870453325 -50919061#3 -50919061#2 -50919061#1 -50919061#0 -229460712#1 -229460712#0 25948331 516863395#0 516863395#1 258194205 150398308 456934817 184156805 150398305 8611964 184156816 184156815 5466445#0 190340312 216879571 674280493 102774826 102749569 4474685 24377358 85287424 85287423#0 187060058#0 187060058#3 187060057#0 42760132 85270645 320185351 320185500#0 320185500#1 320185500#3 270655640 270655641 189899508 360065008 268931669 268931672#0 268931670 268931671 4235244 204207303#0 164095588#2 204207294 150549933#0"/>
    </vehicle>
    <vehicle id="lkw_1800_46" depart="3333.33" type="truck_truck" departLane="best" departSpeed="max" departPos="random">
        <route edges="48278503#2 14189058#0 220914101 286708819 127170001#0 127170001#1 127170001#2 74539230#0 74539230#1 225198733#0 251327592#1 77122439#0 77122439#1 -77122446#3 -77122446#2 -77122446#1 -77122446#0 -30163590#4 -30163590#3 -30163590#2 -30163590#1 -30163590#0 -625333807#1 -625333807#0 -50916530#4 -50916530#3 -50916530#2 -50916530#1 -50916530#0 -870453325 -50919061#3 -50919061#2 -50919061#1 -50919061#0 -229460712#1 -229460712#0 25948331 516863395#0 516863395#1 258194205 150398308 456934817 184156805 150398305 8611964 184156816 184156815 5466445#0 190340312 216879571 674280493 102774826 102749569 17977132 359947001 24388979 187057793#0 190340309 320252264 265910769 320252634#1 320252634#2 320252634#3 320252634#5 320252634#7 320252634#9 320252634#10 288074072#0 288074072#1"/>
    </vehicle>
    <vehicle id="lkw_1800_47" depart="3366.67" type="truck_truck" departLane="best" departSpeed="max" departPos="random">
        <route edges="-870453325 -50919061#3 -50919061#2 -50919061#1 -50919061#0 -229460712#1 -229460712#0 25948331 516863395#0 516863395#1 258194205 150398308 456934817 184156805 150398305 8611964 184156816 184156815 5466445#0 190340312 216879571 674280493 102774826 102749569 4474685 24377358 85287424 85287423#0 187060058#0 187060058#3 187060057#0 42760132 371300204#0 190032739 371300202 35834155#0"/>
    </vehicle>
    <vehicle id="lkw_1800_48" depart="3400.00" type="truck_truck" departLane="best" departSpeed="max" departPos="random">
        <route edges="150395822 25589596 27134171 14189055 5111817 26408353 114976950 74539230#0 74539230#1 225198733#0 251327592#1 77122439#0 77122439#1 -77122446#3 -77122446#2 -77122446#1 -77122446#0 -30163590#4 -30163590#3 -30163590#2 -30163590#1 -30163590#0 -625333807#1 -625333807#0 -50916530#4 -50916530#3 -50916530#2 -50916530#1 -50916530#0 -870453325 -50919061#3 -50919061#2 -50919061#1 -50919061#0 -229460712#1 -229460712#0 25948331 516863395#0 516863395#1 258194205 150398308 456934817 184156805 150398305 8611964 184156816 184156815 184156814#0 184156814#2 150543795 56186952#0"/>
    </vehicle>
    <vehicle id="lkw_1800_49" depart="3433.33" type="truck_truck" departLane="best" departSpeed="max" departPos="random">
        <route edges="-23055466#0 23055466#0 23055466#1 23055466#3 23055466#4 23055466#5 299639054 376865290#0 376865290#1 300034825 472148300 867790499#1 253488980 253488984 149899046 149899941 253488977#0 42760138 187060052 149904354 218778912 268931658 42760136 -531548528 -149942614#1 -149942614#0 4432610#6 4432610#1 4432610#3 4432610#4 -150663778 150663778"/>
    </vehicle>
    <vehicle id="lkw_1800_50" depart="3466.67" type="truck_truck" departLane="best" departSpeed="max" departPos="random">
        <route edges="364080659#1 -364080659#1 -364080659#0 -108404028 253488943 253488947 253488948 253488950#0 112562464 46967473 502060953#0 502060953#1 182065983#1 218778912 268931658 42760136 268931654#1 53040720#2 147683979#0 147683979#2 269001617 269001616 269001621#3 269001620#0 269001620#2 269001619#0 692648169#0 123555933#0 123555933#1 123555933#2 269001612#2 269001612#3 269001612#4 269001612#5"/>
    </vehicle>
    <vehicle id="lkw_1800_51" depart="3500.00" type="truck_truck" departLane="best" departSpeed="max" departPos="random">
        <route edges="258979231#0 258979231#1 144932611 144932612 252753975#1 181335262 293281410#0 258979178#1 251066998 251066997#0 101617775#0 101617775#1 101617775#2 5182256 24909171 251065565 176570669#1 185573957#0 150663777 185573958 237278283 237278282#3 268931664#1 268931665 147683978#0 4084166 268931652 190347317#0 187060053#0"/>
    </vehicle>
    <vehicle id="lkw_1800_52" depart="3533.33" type="truck_truck" departLane="best" departSpeed="max" departPos="random">
        <route edges="24608196#1 24608196#2 -208426932#0 8067185#3 8067185#4 8067185#5 53175161 185576374#0 53175163#1 253488943 253488947 253488948 253488950#0 112562464 46967473 502060953#0 502060953#1 182065983#1 246584302#0 246584302#2 500582850 500582851#1 255389622#0 255389622#3 255389622#4 255389622#5 255389622#6 255389622#8 255389622#9 255389621#0 255389621#1 255389621#2 255389621#3 165849626 165849630#0 150551277#2 363826076 628505596 190431168#1 190431168#2 227062818#1 360248187#3 360248187#4"/>
    </vehicle>
    <vehicle id="lkw_1800_53" depart="3566.67" type="truck_truck" departLane="best" departSpeed="max" departPos="random">
        <route edges="251103977#0 251103977#1 251102620 -127606907#1 127606907#1 251102618 251102624#0 251102624#2 205190519 23567306#0 23567306#1 23567306#2 269040899 190451409 269040904 230602993 190438083#0 190438083#1 269040907#0 269040907#1 204400292 251109201 187060050#2 781345962 300035524 46967474#0 46967474#1 46967473 502060953#0 502060953#1"/>
    </vehicle>
</routes>
